{"events":[{"id":"3a6348a4-b764-4583-8f0f-c52fbb841cf0","session_id":"c21663f7-c35c-4a6f-acdb-6e2afdd9540e","timestamp":"2025-01-27T09:24:40.771Z","type":"lifecycle_view_controller","lifecycle_view_controller":{"type":"viewDidLoad","class_name":"UIInputWindowController"},"attribute":{"thread_name":"com.apple.main-thread","device_name":"iPhone 15 Pro","device_model":"Simulator iPhone 15 Pro","device_manufacturer":"Apple","device_type":"phone","device_is_foldable":false,"device_is_physical":false,"device_density_dpi":480,"device_width_px":1179,"device_height_px":2556,"device_density":3,"device_locale":"en_IN","os_name":"iOS","os_version":"17.4","platform":"ios","network_type":"wifi","network_generation":"unknown","network_provider":"unknown","installation_id":"0289b331-d339-4ff9-9e08-11117afc2327","user_id":"","device_cpu_arch":"x86_64","app_version":"7.5.7","app_build":"0","measure_sdk_version":"0.0.1","device_low_power_mode":false,"app_unique_id":"org.wikimedia.wikipedia"},"user_triggered":false},{"id":"2a3fa667-f20e-447e-9a08-3ae8f8b97fa3","session_id":"c21663f7-c35c-4a6f-acdb-6e2afdd9540e","timestamp":"2025-01-27T09:24:40.779Z","type":"lifecycle_view_controller","lifecycle_view_controller":{"type":"viewWillAppear","class_name":"UIInputWindowController"},"attribute":{"thread_name":"com.apple.main-thread","device_name":"iPhone 15 Pro","device_model":"Simulator iPhone 15 Pro","device_manufacturer":"Apple","device_type":"phone","device_is_foldable":false,"device_is_physical":false,"device_density_dpi":480,"device_width_px":1179,"device_height_px":2556,"device_density":3,"device_locale":"en_IN","os_name":"iOS","os_version":"17.4","platform":"ios","network_type":"wifi","network_generation":"unknown","network_provider":"unknown","installation_id":"0289b331-d339-4ff9-9e08-11117afc2327","user_id":"","device_cpu_arch":"x86_64","app_version":"7.5.7","app_build":"0","measure_sdk_version":"0.0.1","device_low_power_mode":false,"app_unique_id":"org.wikimedia.wikipedia"},"user_triggered":false},{"id":"62b236b4-afdc-4e5c-a820-84ee47fa86a8","session_id":"c21663f7-c35c-4a6f-acdb-6e2afdd9540e","timestamp":"2025-01-27T09:24:40.787Z","type":"lifecycle_view_controller","lifecycle_view_controller":{"type":"viewDidLoad","class_name":"UIEditingOverlayViewController"},"attribute":{"thread_name":"com.apple.main-thread","device_name":"iPhone 15 Pro","device_model":"Simulator iPhone 15 Pro","device_manufacturer":"Apple","device_type":"phone","device_is_foldable":false,"device_is_physical":false,"device_density_dpi":480,"device_width_px":1179,"device_height_px":2556,"device_density":3,"device_locale":"en_IN","os_name":"iOS","os_version":"17.4","platform":"ios","network_type":"wifi","network_generation":"unknown","network_provider":"unknown","installation_id":"0289b331-d339-4ff9-9e08-11117afc2327","user_id":"","device_cpu_arch":"x86_64","app_version":"7.5.7","app_build":"0","measure_sdk_version":"0.0.1","device_low_power_mode":false,"app_unique_id":"org.wikimedia.wikipedia"},"user_triggered":false},{"id":"55ec60d0-5227-4a37-9fef-11193a50c0b9","session_id":"c21663f7-c35c-4a6f-acdb-6e2afdd9540e","timestamp":"2025-01-27T09:24:40.793Z","type":"lifecycle_view_controller","lifecycle_view_controller":{"type":"viewWillAppear","class_name":"UIEditingOverlayViewController"},"attribute":{"thread_name":"com.apple.main-thread","device_name":"iPhone 15 Pro","device_model":"Simulator iPhone 15 Pro","device_manufacturer":"Apple","device_type":"phone","device_is_foldable":false,"device_is_physical":false,"device_density_dpi":480,"device_width_px":1179,"device_height_px":2556,"device_density":3,"device_locale":"en_IN","os_name":"iOS","os_version":"17.4","platform":"ios","network_type":"wifi","network_generation":"unknown","network_provider":"unknown","installation_id":"0289b331-d339-4ff9-9e08-11117afc2327","user_id":"","device_cpu_arch":"x86_64","app_version":"7.5.7","app_build":"0","measure_sdk_version":"0.0.1","device_low_power_mode":false,"app_unique_id":"org.wikimedia.wikipedia"},"user_triggered":false},{"id":"5968f312-7254-4aa2-8e6f-a8393c060835","session_id":"c21663f7-c35c-4a6f-acdb-6e2afdd9540e","timestamp":"2025-01-27T09:24:40.824Z","type":"lifecycle_view_controller","lifecycle_view_controller":{"type":"viewDidAppear","class_name":"UIInputWindowController"},"attribute":{"thread_name":"com.apple.main-thread","device_name":"iPhone 15 Pro","device_model":"Simulator iPhone 15 Pro","device_manufacturer":"Apple","device_type":"phone","device_is_foldable":false,"device_is_physical":false,"device_density_dpi":480,"device_width_px":1179,"device_height_px":2556,"device_density":3,"device_locale":"en_IN","os_name":"iOS","os_version":"17.4","platform":"ios","network_type":"wifi","network_generation":"unknown","network_provider":"unknown","installation_id":"0289b331-d339-4ff9-9e08-11117afc2327","user_id":"","device_cpu_arch":"x86_64","app_version":"7.5.7","app_build":"0","measure_sdk_version":"0.0.1","device_low_power_mode":false,"app_unique_id":"org.wikimedia.wikipedia"},"user_triggered":false},{"id":"40d2bb05-68a1-490f-86e7-6e0ffe0ee17e","session_id":"c21663f7-c35c-4a6f-acdb-6e2afdd9540e","timestamp":"2025-01-27T09:24:41.269Z","type":"cpu_usage","cpu_usage":{"num_cores":12,"clock_speed":2600000000,"start_time":0,"uptime":0,"utime":0,"cutime":0,"cstime":0,"stime":0,"interval":3000,"percentage_usage":9.1},"attribute":{"thread_name":"com.apple.main-thread","device_name":"iPhone 15 Pro","device_model":"Simulator iPhone 15 Pro","device_manufacturer":"Apple","device_type":"phone","device_is_foldable":false,"device_is_physical":false,"device_density_dpi":480,"device_width_px":1179,"device_height_px":2556,"device_density":3,"device_locale":"en_IN","os_name":"iOS","os_version":"17.4","platform":"ios","network_type":"wifi","network_generation":"unknown","network_provider":"unknown","installation_id":"0289b331-d339-4ff9-9e08-11117afc2327","user_id":"","device_cpu_arch":"x86_64","app_version":"7.5.7","app_build":"0","measure_sdk_version":"0.0.1","device_low_power_mode":false,"app_unique_id":"org.wikimedia.wikipedia"},"user_triggered":false},{"id":"597b7642-e8c5-45bc-9197-61e171303b2c","session_id":"c21663f7-c35c-4a6f-acdb-6e2afdd9540e","timestamp":"2025-01-27T09:24:41.276Z","type":"memory_usage_absolute","memory_usage_absolute":{"interval":2000,"used_memory":178868,"max_memory":16777216},"attribute":{"thread_name":"com.apple.main-thread","device_name":"iPhone 15 Pro","device_model":"Simulator iPhone 15 Pro","device_manufacturer":"Apple","device_type":"phone","device_is_foldable":false,"device_is_physical":false,"device_density_dpi":480,"device_width_px":1179,"device_height_px":2556,"device_density":3,"device_locale":"en_IN","os_name":"iOS","os_version":"17.4","platform":"ios","network_type":"wifi","network_generation":"unknown","network_provider":"unknown","installation_id":"0289b331-d339-4ff9-9e08-11117afc2327","user_id":"","device_cpu_arch":"x86_64","app_version":"7.5.7","app_build":"0","measure_sdk_version":"0.0.1","device_low_power_mode":false,"app_unique_id":"org.wikimedia.wikipedia"},"user_triggered":false},{"id":"531cc986-6f73-46b9-9f1e-4cefa0bcfc46","session_id":"c21663f7-c35c-4a6f-acdb-6e2afdd9540e","timestamp":"2025-01-27T09:24:43.094Z","type":"lifecycle_app","lifecycle_app":{"type":"background"},"attribute":{"thread_name":"com.apple.main-thread","device_name":"iPhone 15 Pro","device_model":"Simulator iPhone 15 Pro","device_manufacturer":"Apple","device_type":"phone","device_is_foldable":false,"device_is_physical":false,"device_density_dpi":480,"device_width_px":1179,"device_height_px":2556,"device_density":3,"device_locale":"en_IN","os_name":"iOS","os_version":"17.4","platform":"ios","network_type":"wifi","network_generation":"unknown","network_provider":"unknown","installation_id":"0289b331-d339-4ff9-9e08-11117afc2327","user_id":"","device_cpu_arch":"x86_64","app_version":"7.5.7","app_build":"0","measure_sdk_version":"0.0.1","device_low_power_mode":false,"app_unique_id":"org.wikimedia.wikipedia"},"user_triggered":false},{"id":"6dba276a-ca9a-46c9-8305-b8fe0e2f8d9a","session_id":"c21663f7-c35c-4a6f-acdb-6e2afdd9540e","timestamp":"2025-01-27T09:24:46.325Z","type":"lifecycle_view_controller","lifecycle_view_controller":{"type":"viewWillDisappear","class_name":"ExploreCardViewController"},"attribute":{"thread_name":"com.apple.main-thread","device_name":"iPhone 15 Pro","device_model":"Simulator iPhone 15 Pro","device_manufacturer":"Apple","device_type":"phone","device_is_foldable":false,"device_is_physical":false,"device_density_dpi":480,"device_width_px":1179,"device_height_px":2556,"device_density":3,"device_locale":"en_IN","os_name":"iOS","os_version":"17.4","platform":"ios","network_type":"wifi","network_generation":"unknown","network_provider":"unknown","installation_id":"0289b331-d339-4ff9-9e08-11117afc2327","user_id":"","device_cpu_arch":"x86_64","app_version":"7.5.7","app_build":"0","measure_sdk_version":"0.0.1","device_low_power_mode":false,"app_unique_id":"org.wikimedia.wikipedia"},"user_triggered":false},{"id":"7d847b82-745b-40c7-9d1b-84ad0b1e7e6e","session_id":"c21663f7-c35c-4a6f-acdb-6e2afdd9540e","timestamp":"2025-01-27T09:24:46.351Z","type":"lifecycle_app","lifecycle_app":{"type":"foreground"},"attribute":{"thread_name":"com.apple.main-thread","device_name":"iPhone 15 Pro","device_model":"Simulator iPhone 15 Pro","device_manufacturer":"Apple","device_type":"phone","device_is_foldable":false,"device_is_physical":false,"device_density_dpi":480,"device_width_px":1179,"device_height_px":2556,"device_density":3,"device_locale":"en_IN","os_name":"iOS","os_version":"17.4","platform":"ios","network_type":"wifi","network_generation":"unknown","network_provider":"unknown","installation_id":"0289b331-d339-4ff9-9e08-11117afc2327","user_id":"","device_cpu_arch":"x86_64","app_version":"7.5.7","app_build":"0","measure_sdk_version":"0.0.1","device_low_power_mode":false,"app_unique_id":"org.wikimedia.wikipedia"},"user_triggered":false},{"id":"e96ff01f-b959-4c95-adc4-dec0b1495c3f","session_id":"c21663f7-c35c-4a6f-acdb-6e2afdd9540e","timestamp":"2025-01-27T09:24:46.451Z","type":"lifecycle_view_controller","lifecycle_view_controller":{"type":"viewDidDisappear","class_name":"ExploreCardViewController"},"attribute":{"thread_name":"com.apple.main-thread","device_name":"iPhone 15 Pro","device_model":"Simulator iPhone 15 Pro","device_manufacturer":"Apple","device_type":"phone","device_is_foldable":false,"device_is_physical":false,"device_density_dpi":480,"device_width_px":1179,"device_height_px":2556,"device_density":3,"device_locale":"en_IN","os_name":"iOS","os_version":"17.4","platform":"ios","network_type":"wifi","network_generation":"unknown","network_provider":"unknown","installation_id":"0289b331-d339-4ff9-9e08-11117afc2327","user_id":"","device_cpu_arch":"x86_64","app_version":"7.5.7","app_build":"0","measure_sdk_version":"0.0.1","device_low_power_mode":false,"app_unique_id":"org.wikimedia.wikipedia"},"user_triggered":false}]}