{"events":[{"id":"e264688f-0268-4c0d-9cb2-687a25f5c703","session_id":"d488ad4d-6f40-43a5-8ca3-a504245d3fe6","timestamp":"2025-03-15T11:15:51.225Z","type":"warm_launch","warm_launch":{"app_visible_uptime":1742037350000,"on_next_draw_uptime":1742037351224,"launched_activity":"UINavigationController","has_saved_state":false,"intent_data":""},"attribute":{"thread_name":"com.apple.main-thread","device_name":"iPhone 16 Pro","device_model":"Simulator iPhone17,1","device_manufacturer":"Apple","device_type":"phone","device_is_foldable":false,"device_is_physical":false,"device_density_dpi":480,"device_width_px":1206,"device_height_px":2622,"device_density":3,"device_locale":"en_IN","os_name":"iOS","os_version":"18.3.1","platform":"ios","network_type":"wifi","network_generation":"unknown","network_provider":"unknown","installation_id":"98aa4d46-a856-45a9-b521-f4566532b572","user_id":"test_user_ios","device_cpu_arch":"arm64e","app_version":"1.0.0","app_build":"2","measure_sdk_version":"0.0.1","device_low_power_mode":false,"app_unique_id":"sh.measure.DemoApp"},"user_triggered":false},{"id":"42a10d7d-9c2f-4586-a97e-067390d3256a","session_id":"d488ad4d-6f40-43a5-8ca3-a504245d3fe6","timestamp":"2025-03-15T11:15:51.231Z","type":"lifecycle_view_controller","lifecycle_view_controller":{"type":"viewDidAppear","class_name":"UINavigationController"},"attribute":{"thread_name":"com.apple.main-thread","device_name":"iPhone 16 Pro","device_model":"Simulator iPhone17,1","device_manufacturer":"Apple","device_type":"phone","device_is_foldable":false,"device_is_physical":false,"device_density_dpi":480,"device_width_px":1206,"device_height_px":2622,"device_density":3,"device_locale":"en_IN","os_name":"iOS","os_version":"18.3.1","platform":"ios","network_type":"wifi","network_generation":"unknown","network_provider":"unknown","installation_id":"98aa4d46-a856-45a9-b521-f4566532b572","user_id":"test_user_ios","device_cpu_arch":"arm64e","app_version":"1.0.0","app_build":"2","measure_sdk_version":"0.0.1","device_low_power_mode":false,"app_unique_id":"sh.measure.DemoApp"},"user_triggered":false},{"id":"82a47294-2744-4931-97e9-a8af72712310","session_id":"d488ad4d-6f40-43a5-8ca3-a504245d3fe6","timestamp":"2025-03-15T11:15:51.233Z","type":"lifecycle_view_controller","lifecycle_view_controller":{"type":"viewDidAppear","class_name":"ViewController"},"attribute":{"thread_name":"com.apple.main-thread","device_name":"iPhone 16 Pro","device_model":"Simulator iPhone17,1","device_manufacturer":"Apple","device_type":"phone","device_is_foldable":false,"device_is_physical":false,"device_density_dpi":480,"device_width_px":1206,"device_height_px":2622,"device_density":3,"device_locale":"en_IN","os_name":"iOS","os_version":"18.3.1","platform":"ios","network_type":"wifi","network_generation":"unknown","network_provider":"unknown","installation_id":"98aa4d46-a856-45a9-b521-f4566532b572","user_id":"test_user_ios","device_cpu_arch":"arm64e","app_version":"1.0.0","app_build":"2","measure_sdk_version":"0.0.1","device_low_power_mode":false,"app_unique_id":"sh.measure.DemoApp"},"user_triggered":false},{"id":"66a9cedf-6f4e-4eca-bc7f-9255686636a3","session_id":"d488ad4d-6f40-43a5-8ca3-a504245d3fe6","timestamp":"2025-03-15T11:15:51.236Z","type":"screen_view","screen_view":{"name":"Home"},"attribute":{"thread_name":"com.apple.main-thread","device_name":"iPhone 16 Pro","device_model":"Simulator iPhone17,1","device_manufacturer":"Apple","device_type":"phone","device_is_foldable":false,"device_is_physical":false,"device_density_dpi":480,"device_width_px":1206,"device_height_px":2622,"device_density":3,"device_locale":"en_IN","os_name":"iOS","os_version":"18.3.1","platform":"ios","network_type":"wifi","network_generation":"unknown","network_provider":"unknown","installation_id":"98aa4d46-a856-45a9-b521-f4566532b572","user_id":"test_user_ios","device_cpu_arch":"arm64e","app_version":"1.0.0","app_build":"2","measure_sdk_version":"0.0.1","device_low_power_mode":false,"app_unique_id":"sh.measure.DemoApp"},"user_triggered":true},{"id":"7265cf22-8766-4665-8689-ababd4c1fcfe","session_id":"d488ad4d-6f40-43a5-8ca3-a504245d3fe6","timestamp":"2025-03-15T11:15:53.099Z","type":"memory_usage_absolute","memory_usage_absolute":{"interval":2000,"used_memory":25090,"max_memory":25165824},"attribute":{"thread_name":"com.apple.main-thread","device_name":"iPhone 16 Pro","device_model":"Simulator iPhone17,1","device_manufacturer":"Apple","device_type":"phone","device_is_foldable":false,"device_is_physical":false,"device_density_dpi":480,"device_width_px":1206,"device_height_px":2622,"device_density":3,"device_locale":"en_IN","os_name":"iOS","os_version":"18.3.1","platform":"ios","network_type":"wifi","network_generation":"unknown","network_provider":"unknown","installation_id":"98aa4d46-a856-45a9-b521-f4566532b572","user_id":"test_user_ios","device_cpu_arch":"arm64e","app_version":"1.0.0","app_build":"2","measure_sdk_version":"0.0.1","device_low_power_mode":false,"app_unique_id":"sh.measure.DemoApp"},"user_triggered":false},{"id":"c97d991c-50e9-4ed6-aa9f-ca53d1aeb481","session_id":"d488ad4d-6f40-43a5-8ca3-a504245d3fe6","timestamp":"2025-03-15T11:15:53.525Z","type":"gesture_scroll","gesture_scroll":{"target":"UITableView","target_id":"HomeTableView","x":193.0,"y":617.6666,"end_x":193.0,"end_y":461.0,"direction":"up","touch_down_time":124398313,"touch_up_time":124398551},"attribute":{"thread_name":"com.apple.main-thread","device_name":"iPhone 16 Pro","device_model":"Simulator iPhone17,1","device_manufacturer":"Apple","device_type":"phone","device_is_foldable":false,"device_is_physical":false,"device_density_dpi":480,"device_width_px":1206,"device_height_px":2622,"device_density":3,"device_locale":"en_IN","os_name":"iOS","os_version":"18.3.1","platform":"ios","network_type":"wifi","network_generation":"unknown","network_provider":"unknown","installation_id":"98aa4d46-a856-45a9-b521-f4566532b572","user_id":"test_user_ios","device_cpu_arch":"arm64e","app_version":"1.0.0","app_build":"2","measure_sdk_version":"0.0.1","device_low_power_mode":false,"app_unique_id":"sh.measure.DemoApp"},"attachments":[{"id":"b5d03eeb-3411-4ce6-ad1d-2fc2142faa10","name":"layoutSnapshot.svg","type":"layout_snapshot"}],"user_triggered":false},{"id":"1b64d20c-a831-48ab-b149-b66b7c48ec4e","session_id":"d488ad4d-6f40-43a5-8ca3-a504245d3fe6","timestamp":"2025-03-15T11:15:54.196Z","type":"gesture_scroll","gesture_scroll":{"target":"UITableView","target_id":"HomeTableView","x":193.0,"y":458.0,"end_x":193.0,"end_y":639.0,"direction":"down","touch_down_time":124399053,"touch_up_time":124399223},"attribute":{"thread_name":"com.apple.main-thread","device_name":"iPhone 16 Pro","device_model":"Simulator iPhone17,1","device_manufacturer":"Apple","device_type":"phone","device_is_foldable":false,"device_is_physical":false,"device_density_dpi":480,"device_width_px":1206,"device_height_px":2622,"device_density":3,"device_locale":"en_IN","os_name":"iOS","os_version":"18.3.1","platform":"ios","network_type":"wifi","network_generation":"unknown","network_provider":"unknown","installation_id":"98aa4d46-a856-45a9-b521-f4566532b572","user_id":"test_user_ios","device_cpu_arch":"arm64e","app_version":"1.0.0","app_build":"2","measure_sdk_version":"0.0.1","device_low_power_mode":false,"app_unique_id":"sh.measure.DemoApp"},"user_triggered":false},{"id":"0027a9a3-2a77-407c-b93f-4fdc4f9d799e","session_id":"d488ad4d-6f40-43a5-8ca3-a504245d3fe6","timestamp":"2025-03-15T11:15:54.958Z","type":"cpu_usage","cpu_usage":{"num_cores":14,"clock_speed":4500000000,"start_time":0,"uptime":0,"utime":0,"cutime":0,"cstime":0,"stime":0,"interval":3000,"percentage_usage":6.4},"attribute":{"thread_name":"com.apple.main-thread","device_name":"iPhone 16 Pro","device_model":"Simulator iPhone17,1","device_manufacturer":"Apple","device_type":"phone","device_is_foldable":false,"device_is_physical":false,"device_density_dpi":480,"device_width_px":1206,"device_height_px":2622,"device_density":3,"device_locale":"en_IN","os_name":"iOS","os_version":"18.3.1","platform":"ios","network_type":"wifi","network_generation":"unknown","network_provider":"unknown","installation_id":"98aa4d46-a856-45a9-b521-f4566532b572","user_id":"test_user_ios","device_cpu_arch":"arm64e","app_version":"1.0.0","app_build":"2","measure_sdk_version":"0.0.1","device_low_power_mode":false,"app_unique_id":"sh.measure.DemoApp"},"user_triggered":false},{"id":"5bbf2b2b-08de-4940-a2a1-ebdee7dc31d2","session_id":"d488ad4d-6f40-43a5-8ca3-a504245d3fe6","timestamp":"2025-03-15T11:15:55.098Z","type":"memory_usage_absolute","memory_usage_absolute":{"interval":2000,"used_memory":25906,"max_memory":25165824},"attribute":{"thread_name":"com.apple.main-thread","device_name":"iPhone 16 Pro","device_model":"Simulator iPhone17,1","device_manufacturer":"Apple","device_type":"phone","device_is_foldable":false,"device_is_physical":false,"device_density_dpi":480,"device_width_px":1206,"device_height_px":2622,"device_density":3,"device_locale":"en_IN","os_name":"iOS","os_version":"18.3.1","platform":"ios","network_type":"wifi","network_generation":"unknown","network_provider":"unknown","installation_id":"98aa4d46-a856-45a9-b521-f4566532b572","user_id":"test_user_ios","device_cpu_arch":"arm64e","app_version":"1.0.0","app_build":"2","measure_sdk_version":"0.0.1","device_low_power_mode":false,"app_unique_id":"sh.measure.DemoApp"},"user_triggered":false},{"id":"8c7a60d5-21e3-4d01-8c07-27e924baadd2","session_id":"d488ad4d-6f40-43a5-8ca3-a504245d3fe6","timestamp":"2025-03-15T11:15:55.215Z","type":"gesture_click","gesture_click":{"target":"UIButton","target_id":"","width":173,"height":63,"x":294.0,"y":225.66666,"touch_down_time":124400138,"touch_up_time":124400241},"attribute":{"thread_name":"com.apple.main-thread","device_name":"iPhone 16 Pro","device_model":"Simulator iPhone17,1","device_manufacturer":"Apple","device_type":"phone","device_is_foldable":false,"device_is_physical":false,"device_density_dpi":480,"device_width_px":1206,"device_height_px":2622,"device_density":3,"device_locale":"en_IN","os_name":"iOS","os_version":"18.3.1","platform":"ios","network_type":"wifi","network_generation":"unknown","network_provider":"unknown","installation_id":"98aa4d46-a856-45a9-b521-f4566532b572","user_id":"test_user_ios","device_cpu_arch":"arm64e","app_version":"1.0.0","app_build":"2","measure_sdk_version":"0.0.1","device_low_power_mode":false,"app_unique_id":"sh.measure.DemoApp"},"attachments":[{"id":"ced00e5e-bc01-4715-8f19-ef1106cbd318","name":"layoutSnapshot.svg","type":"layout_snapshot"}],"user_triggered":false},{"id":"51c09780-904d-46db-916a-5c270fdafc53","session_id":"d488ad4d-6f40-43a5-8ca3-a504245d3fe6","timestamp":"2025-03-15T11:15:55.234Z","type":"lifecycle_view_controller","lifecycle_view_controller":{"type":"viewDidLoad","class_name":"ControlsViewController"},"attribute":{"thread_name":"com.apple.main-thread","device_name":"iPhone 16 Pro","device_model":"Simulator iPhone17,1","device_manufacturer":"Apple","device_type":"phone","device_is_foldable":false,"device_is_physical":false,"device_density_dpi":480,"device_width_px":1206,"device_height_px":2622,"device_density":3,"device_locale":"en_IN","os_name":"iOS","os_version":"18.3.1","platform":"ios","network_type":"wifi","network_generation":"unknown","network_provider":"unknown","installation_id":"98aa4d46-a856-45a9-b521-f4566532b572","user_id":"test_user_ios","device_cpu_arch":"arm64e","app_version":"1.0.0","app_build":"2","measure_sdk_version":"0.0.1","device_low_power_mode":false,"app_unique_id":"sh.measure.DemoApp"},"user_triggered":false},{"id":"c127865f-c547-4a45-9fda-c9b534269777","session_id":"d488ad4d-6f40-43a5-8ca3-a504245d3fe6","timestamp":"2025-03-15T11:15:55.238Z","type":"lifecycle_view_controller","lifecycle_view_controller":{"type":"viewWillDisappear","class_name":"ViewController"},"attribute":{"thread_name":"com.apple.main-thread","device_name":"iPhone 16 Pro","device_model":"Simulator iPhone17,1","device_manufacturer":"Apple","device_type":"phone","device_is_foldable":false,"device_is_physical":false,"device_density_dpi":480,"device_width_px":1206,"device_height_px":2622,"device_density":3,"device_locale":"en_IN","os_name":"iOS","os_version":"18.3.1","platform":"ios","network_type":"wifi","network_generation":"unknown","network_provider":"unknown","installation_id":"98aa4d46-a856-45a9-b521-f4566532b572","user_id":"test_user_ios","device_cpu_arch":"arm64e","app_version":"1.0.0","app_build":"2","measure_sdk_version":"0.0.1","device_low_power_mode":false,"app_unique_id":"sh.measure.DemoApp"},"user_triggered":false},{"id":"b9df8e4a-e29d-449e-8184-cf57e0381a91","session_id":"d488ad4d-6f40-43a5-8ca3-a504245d3fe6","timestamp":"2025-03-15T11:15:55.242Z","type":"lifecycle_view_controller","lifecycle_view_controller":{"type":"viewWillAppear","class_name":"ControlsViewController"},"attribute":{"thread_name":"com.apple.main-thread","device_name":"iPhone 16 Pro","device_model":"Simulator iPhone17,1","device_manufacturer":"Apple","device_type":"phone","device_is_foldable":false,"device_is_physical":false,"device_density_dpi":480,"device_width_px":1206,"device_height_px":2622,"device_density":3,"device_locale":"en_IN","os_name":"iOS","os_version":"18.3.1","platform":"ios","network_type":"wifi","network_generation":"unknown","network_provider":"unknown","installation_id":"98aa4d46-a856-45a9-b521-f4566532b572","user_id":"test_user_ios","device_cpu_arch":"arm64e","app_version":"1.0.0","app_build":"2","measure_sdk_version":"0.0.1","device_low_power_mode":false,"app_unique_id":"sh.measure.DemoApp"},"user_triggered":false},{"id":"425a224b-9c73-46a1-a79b-7ead512e1b83","session_id":"d488ad4d-6f40-43a5-8ca3-a504245d3fe6","timestamp":"2025-03-15T11:15:55.769Z","type":"lifecycle_view_controller","lifecycle_view_controller":{"type":"viewDidDisappear","class_name":"ViewController"},"attribute":{"thread_name":"com.apple.main-thread","device_name":"iPhone 16 Pro","device_model":"Simulator iPhone17,1","device_manufacturer":"Apple","device_type":"phone","device_is_foldable":false,"device_is_physical":false,"device_density_dpi":480,"device_width_px":1206,"device_height_px":2622,"device_density":3,"device_locale":"en_IN","os_name":"iOS","os_version":"18.3.1","platform":"ios","network_type":"wifi","network_generation":"unknown","network_provider":"unknown","installation_id":"98aa4d46-a856-45a9-b521-f4566532b572","user_id":"test_user_ios","device_cpu_arch":"arm64e","app_version":"1.0.0","app_build":"2","measure_sdk_version":"0.0.1","device_low_power_mode":false,"app_unique_id":"sh.measure.DemoApp"},"user_triggered":false},{"id":"a26e074b-4112-4bd2-89bf-ff1de18a2dda","session_id":"d488ad4d-6f40-43a5-8ca3-a504245d3fe6","timestamp":"2025-03-15T11:15:55.778Z","type":"custom","custom":{"name":"custom_event"},"attribute":{"thread_name":"com.apple.main-thread","device_name":"iPhone 16 Pro","device_model":"Simulator iPhone17,1","device_manufacturer":"Apple","device_type":"phone","device_is_foldable":false,"device_is_physical":false,"device_density_dpi":480,"device_width_px":1206,"device_height_px":2622,"device_density":3,"device_locale":"en_IN","os_name":"iOS","os_version":"18.3.1","platform":"ios","network_type":"wifi","network_generation":"unknown","network_provider":"unknown","installation_id":"98aa4d46-a856-45a9-b521-f4566532b572","user_id":"test_user_ios","device_cpu_arch":"arm64e","app_version":"1.0.0","app_build":"2","measure_sdk_version":"0.0.1","device_low_power_mode":false,"app_unique_id":"sh.measure.DemoApp"},"user_defined_attribute":{"paid_user":true,"latitude":30.2661403415387,"credit_balance":1000,"user_name":"Alice"},"user_triggered":true},{"id":"34003770-c3c1-417a-8925-2987540c7900","session_id":"d488ad4d-6f40-43a5-8ca3-a504245d3fe6","timestamp":"2025-03-15T11:15:55.784Z","type":"lifecycle_view_controller","lifecycle_view_controller":{"type":"viewDidAppear","class_name":"ControlsViewController"},"attribute":{"thread_name":"com.apple.main-thread","device_name":"iPhone 16 Pro","device_model":"Simulator iPhone17,1","device_manufacturer":"Apple","device_type":"phone","device_is_foldable":false,"device_is_physical":false,"device_density_dpi":480,"device_width_px":1206,"device_height_px":2622,"device_density":3,"device_locale":"en_IN","os_name":"iOS","os_version":"18.3.1","platform":"ios","network_type":"wifi","network_generation":"unknown","network_provider":"unknown","installation_id":"98aa4d46-a856-45a9-b521-f4566532b572","user_id":"test_user_ios","device_cpu_arch":"arm64e","app_version":"1.0.0","app_build":"2","measure_sdk_version":"0.0.1","device_low_power_mode":false,"app_unique_id":"sh.measure.DemoApp"},"user_triggered":false},{"id":"c65e6a6a-8c40-4894-bee6-a738a650c8ec","session_id":"d488ad4d-6f40-43a5-8ca3-a504245d3fe6","timestamp":"2025-03-15T11:15:56.775Z","type":"gesture_click","gesture_click":{"target":"UISegmentedControl","target_id":"","width":131,"height":32,"x":228.33333,"y":116.66666,"touch_down_time":124401690,"touch_up_time":124401801},"attribute":{"thread_name":"com.apple.main-thread","device_name":"iPhone 16 Pro","device_model":"Simulator iPhone17,1","device_manufacturer":"Apple","device_type":"phone","device_is_foldable":false,"device_is_physical":false,"device_density_dpi":480,"device_width_px":1206,"device_height_px":2622,"device_density":3,"device_locale":"en_IN","os_name":"iOS","os_version":"18.3.1","platform":"ios","network_type":"wifi","network_generation":"unknown","network_provider":"unknown","installation_id":"98aa4d46-a856-45a9-b521-f4566532b572","user_id":"test_user_ios","device_cpu_arch":"arm64e","app_version":"1.0.0","app_build":"2","measure_sdk_version":"0.0.1","device_low_power_mode":false,"app_unique_id":"sh.measure.DemoApp"},"attachments":[{"id":"2b9f180b-8e96-4ccd-9150-6c5da4aab9f8","name":"layoutSnapshot.svg","type":"layout_snapshot"}],"user_triggered":false},{"id":"e31eab9a-1179-47b4-9fc4-03c681de8745","session_id":"d488ad4d-6f40-43a5-8ca3-a504245d3fe6","timestamp":"2025-03-15T11:15:56.788Z","type":"lifecycle_view_controller","lifecycle_view_controller":{"type":"viewDidLoad","class_name":"_UIAlertControllerTextFieldViewController"},"attribute":{"thread_name":"com.apple.main-thread","device_name":"iPhone 16 Pro","device_model":"Simulator iPhone17,1","device_manufacturer":"Apple","device_type":"phone","device_is_foldable":false,"device_is_physical":false,"device_density_dpi":480,"device_width_px":1206,"device_height_px":2622,"device_density":3,"device_locale":"en_IN","os_name":"iOS","os_version":"18.3.1","platform":"ios","network_type":"wifi","network_generation":"unknown","network_provider":"unknown","installation_id":"98aa4d46-a856-45a9-b521-f4566532b572","user_id":"test_user_ios","device_cpu_arch":"arm64e","app_version":"1.0.0","app_build":"2","measure_sdk_version":"0.0.1","device_low_power_mode":false,"app_unique_id":"sh.measure.DemoApp"},"user_triggered":false},{"id":"10b352cf-4d46-4053-a6fe-c0c43b260e18","session_id":"d488ad4d-6f40-43a5-8ca3-a504245d3fe6","timestamp":"2025-03-15T11:15:56.799Z","type":"lifecycle_view_controller","lifecycle_view_controller":{"type":"viewDidLoad","class_name":"UIAlertController"},"attribute":{"thread_name":"com.apple.main-thread","device_name":"iPhone 16 Pro","device_model":"Simulator iPhone17,1","device_manufacturer":"Apple","device_type":"phone","device_is_foldable":false,"device_is_physical":false,"device_density_dpi":480,"device_width_px":1206,"device_height_px":2622,"device_density":3,"device_locale":"en_IN","os_name":"iOS","os_version":"18.3.1","platform":"ios","network_type":"wifi","network_generation":"unknown","network_provider":"unknown","installation_id":"98aa4d46-a856-45a9-b521-f4566532b572","user_id":"test_user_ios","device_cpu_arch":"arm64e","app_version":"1.0.0","app_build":"2","measure_sdk_version":"0.0.1","device_low_power_mode":false,"app_unique_id":"sh.measure.DemoApp"},"user_triggered":false},{"id":"5d873edb-f4a8-4560-83ba-53a2e436eb57","session_id":"d488ad4d-6f40-43a5-8ca3-a504245d3fe6","timestamp":"2025-03-15T11:15:56.851Z","type":"lifecycle_view_controller","lifecycle_view_controller":{"type":"viewDidLoad","class_name":"UIInputWindowController"},"attribute":{"thread_name":"com.apple.main-thread","device_name":"iPhone 16 Pro","device_model":"Simulator iPhone17,1","device_manufacturer":"Apple","device_type":"phone","device_is_foldable":false,"device_is_physical":false,"device_density_dpi":480,"device_width_px":1206,"device_height_px":2622,"device_density":3,"device_locale":"en_IN","os_name":"iOS","os_version":"18.3.1","platform":"ios","network_type":"wifi","network_generation":"unknown","network_provider":"unknown","installation_id":"98aa4d46-a856-45a9-b521-f4566532b572","user_id":"test_user_ios","device_cpu_arch":"arm64e","app_version":"1.0.0","app_build":"2","measure_sdk_version":"0.0.1","device_low_power_mode":false,"app_unique_id":"sh.measure.DemoApp"},"user_triggered":false},{"id":"f29957c4-22b8-4229-94b0-9ef3936bc246","session_id":"d488ad4d-6f40-43a5-8ca3-a504245d3fe6","timestamp":"2025-03-15T11:15:56.859Z","type":"lifecycle_view_controller","lifecycle_view_controller":{"type":"viewWillAppear","class_name":"UIInputWindowController"},"attribute":{"thread_name":"com.apple.main-thread","device_name":"iPhone 16 Pro","device_model":"Simulator iPhone17,1","device_manufacturer":"Apple","device_type":"phone","device_is_foldable":false,"device_is_physical":false,"device_density_dpi":480,"device_width_px":1206,"device_height_px":2622,"device_density":3,"device_locale":"en_IN","os_name":"iOS","os_version":"18.3.1","platform":"ios","network_type":"wifi","network_generation":"unknown","network_provider":"unknown","installation_id":"98aa4d46-a856-45a9-b521-f4566532b572","user_id":"test_user_ios","device_cpu_arch":"arm64e","app_version":"1.0.0","app_build":"2","measure_sdk_version":"0.0.1","device_low_power_mode":false,"app_unique_id":"sh.measure.DemoApp"},"user_triggered":false},{"id":"bae1fa29-0389-4fa8-a263-215b701caa84","session_id":"d488ad4d-6f40-43a5-8ca3-a504245d3fe6","timestamp":"2025-03-15T11:15:56.866Z","type":"lifecycle_view_controller","lifecycle_view_controller":{"type":"viewDidLoad","class_name":"UIEditingOverlayViewController"},"attribute":{"thread_name":"com.apple.main-thread","device_name":"iPhone 16 Pro","device_model":"Simulator iPhone17,1","device_manufacturer":"Apple","device_type":"phone","device_is_foldable":false,"device_is_physical":false,"device_density_dpi":480,"device_width_px":1206,"device_height_px":2622,"device_density":3,"device_locale":"en_IN","os_name":"iOS","os_version":"18.3.1","platform":"ios","network_type":"wifi","network_generation":"unknown","network_provider":"unknown","installation_id":"98aa4d46-a856-45a9-b521-f4566532b572","user_id":"test_user_ios","device_cpu_arch":"arm64e","app_version":"1.0.0","app_build":"2","measure_sdk_version":"0.0.1","device_low_power_mode":false,"app_unique_id":"sh.measure.DemoApp"},"user_triggered":false},{"id":"cc91417a-8da3-4124-95e0-90f0c8aa5efa","session_id":"d488ad4d-6f40-43a5-8ca3-a504245d3fe6","timestamp":"2025-03-15T11:15:56.868Z","type":"lifecycle_view_controller","lifecycle_view_controller":{"type":"viewWillAppear","class_name":"UIEditingOverlayViewController"},"attribute":{"thread_name":"com.apple.main-thread","device_name":"iPhone 16 Pro","device_model":"Simulator iPhone17,1","device_manufacturer":"Apple","device_type":"phone","device_is_foldable":false,"device_is_physical":false,"device_density_dpi":480,"device_width_px":1206,"device_height_px":2622,"device_density":3,"device_locale":"en_IN","os_name":"iOS","os_version":"18.3.1","platform":"ios","network_type":"wifi","network_generation":"unknown","network_provider":"unknown","installation_id":"98aa4d46-a856-45a9-b521-f4566532b572","user_id":"test_user_ios","device_cpu_arch":"arm64e","app_version":"1.0.0","app_build":"2","measure_sdk_version":"0.0.1","device_low_power_mode":false,"app_unique_id":"sh.measure.DemoApp"},"user_triggered":false},{"id":"9d14b69f-3835-4eb1-9ce8-83126e2babf8","session_id":"d488ad4d-6f40-43a5-8ca3-a504245d3fe6","timestamp":"2025-03-15T11:15:56.872Z","type":"lifecycle_view_controller","lifecycle_view_controller":{"type":"viewWillAppear","class_name":"UIAlertController"},"attribute":{"thread_name":"com.apple.main-thread","device_name":"iPhone 16 Pro","device_model":"Simulator iPhone17,1","device_manufacturer":"Apple","device_type":"phone","device_is_foldable":false,"device_is_physical":false,"device_density_dpi":480,"device_width_px":1206,"device_height_px":2622,"device_density":3,"device_locale":"en_IN","os_name":"iOS","os_version":"18.3.1","platform":"ios","network_type":"wifi","network_generation":"unknown","network_provider":"unknown","installation_id":"98aa4d46-a856-45a9-b521-f4566532b572","user_id":"test_user_ios","device_cpu_arch":"arm64e","app_version":"1.0.0","app_build":"2","measure_sdk_version":"0.0.1","device_low_power_mode":false,"app_unique_id":"sh.measure.DemoApp"},"user_triggered":false},{"id":"2a01883f-af67-4204-809a-4339d95eb093","session_id":"d488ad4d-6f40-43a5-8ca3-a504245d3fe6","timestamp":"2025-03-15T11:15:56.879Z","type":"lifecycle_view_controller","lifecycle_view_controller":{"type":"viewDidAppear","class_name":"UIInputWindowController"},"attribute":{"thread_name":"com.apple.main-thread","device_name":"iPhone 16 Pro","device_model":"Simulator iPhone17,1","device_manufacturer":"Apple","device_type":"phone","device_is_foldable":false,"device_is_physical":false,"device_density_dpi":480,"device_width_px":1206,"device_height_px":2622,"device_density":3,"device_locale":"en_IN","os_name":"iOS","os_version":"18.3.1","platform":"ios","network_type":"wifi","network_generation":"unknown","network_provider":"unknown","installation_id":"98aa4d46-a856-45a9-b521-f4566532b572","user_id":"test_user_ios","device_cpu_arch":"arm64e","app_version":"1.0.0","app_build":"2","measure_sdk_version":"0.0.1","device_low_power_mode":false,"app_unique_id":"sh.measure.DemoApp"},"user_triggered":false},{"id":"32a3060f-7438-4228-b9e1-7395851e6e5d","session_id":"d488ad4d-6f40-43a5-8ca3-a504245d3fe6","timestamp":"2025-03-15T11:15:57.099Z","type":"cpu_usage","cpu_usage":{"num_cores":14,"clock_speed":4500000000,"start_time":0,"uptime":0,"utime":0,"cutime":0,"cstime":0,"stime":0,"interval":3000,"percentage_usage":61.400000000000006},"attribute":{"thread_name":"com.apple.main-thread","device_name":"iPhone 16 Pro","device_model":"Simulator iPhone17,1","device_manufacturer":"Apple","device_type":"phone","device_is_foldable":false,"device_is_physical":false,"device_density_dpi":480,"device_width_px":1206,"device_height_px":2622,"device_density":3,"device_locale":"en_IN","os_name":"iOS","os_version":"18.3.1","platform":"ios","network_type":"wifi","network_generation":"unknown","network_provider":"unknown","installation_id":"98aa4d46-a856-45a9-b521-f4566532b572","user_id":"test_user_ios","device_cpu_arch":"arm64e","app_version":"1.0.0","app_build":"2","measure_sdk_version":"0.0.1","device_low_power_mode":false,"app_unique_id":"sh.measure.DemoApp"},"user_triggered":false},{"id":"6b2745b5-b386-499b-83c7-faabb416d4fe","session_id":"d488ad4d-6f40-43a5-8ca3-a504245d3fe6","timestamp":"2025-03-15T11:15:57.110Z","type":"memory_usage_absolute","memory_usage_absolute":{"interval":2000,"used_memory":27778,"max_memory":25165824},"attribute":{"thread_name":"com.apple.main-thread","device_name":"iPhone 16 Pro","device_model":"Simulator iPhone17,1","device_manufacturer":"Apple","device_type":"phone","device_is_foldable":false,"device_is_physical":false,"device_density_dpi":480,"device_width_px":1206,"device_height_px":2622,"device_density":3,"device_locale":"en_IN","os_name":"iOS","os_version":"18.3.1","platform":"ios","network_type":"wifi","network_generation":"unknown","network_provider":"unknown","installation_id":"98aa4d46-a856-45a9-b521-f4566532b572","user_id":"test_user_ios","device_cpu_arch":"arm64e","app_version":"1.0.0","app_build":"2","measure_sdk_version":"0.0.1","device_low_power_mode":false,"app_unique_id":"sh.measure.DemoApp"},"user_triggered":false},{"id":"af9cf4dd-3ec3-4d5f-bda4-7a8626fc3982","session_id":"d488ad4d-6f40-43a5-8ca3-a504245d3fe6","timestamp":"2025-03-15T11:15:57.286Z","type":"lifecycle_view_controller","lifecycle_view_controller":{"type":"viewDidAppear","class_name":"UIAlertController"},"attribute":{"thread_name":"com.apple.main-thread","device_name":"iPhone 16 Pro","device_model":"Simulator iPhone17,1","device_manufacturer":"Apple","device_type":"phone","device_is_foldable":false,"device_is_physical":false,"device_density_dpi":480,"device_width_px":1206,"device_height_px":2622,"device_density":3,"device_locale":"en_IN","os_name":"iOS","os_version":"18.3.1","platform":"ios","network_type":"wifi","network_generation":"unknown","network_provider":"unknown","installation_id":"98aa4d46-a856-45a9-b521-f4566532b572","user_id":"test_user_ios","device_cpu_arch":"arm64e","app_version":"1.0.0","app_build":"2","measure_sdk_version":"0.0.1","device_low_power_mode":false,"app_unique_id":"sh.measure.DemoApp"},"user_triggered":false},{"id":"5583c215-ca72-4c63-884a-36e1c060d4f3","session_id":"d488ad4d-6f40-43a5-8ca3-a504245d3fe6","timestamp":"2025-03-15T11:15:58.034Z","type":"gesture_click","gesture_click":{"target":"_UIAlertControllerActionView","target_id":"","width":134,"height":44,"x":244.0,"y":487.3333,"touch_down_time":124402959,"touch_up_time":124403058},"attribute":{"thread_name":"com.apple.main-thread","device_name":"iPhone 16 Pro","device_model":"Simulator iPhone17,1","device_manufacturer":"Apple","device_type":"phone","device_is_foldable":false,"device_is_physical":false,"device_density_dpi":480,"device_width_px":1206,"device_height_px":2622,"device_density":3,"device_locale":"en_IN","os_name":"iOS","os_version":"18.3.1","platform":"ios","network_type":"wifi","network_generation":"unknown","network_provider":"unknown","installation_id":"98aa4d46-a856-45a9-b521-f4566532b572","user_id":"test_user_ios","device_cpu_arch":"arm64e","app_version":"1.0.0","app_build":"2","measure_sdk_version":"0.0.1","device_low_power_mode":false,"app_unique_id":"sh.measure.DemoApp"},"attachments":[{"id":"076c5ce1-08a3-4e02-bffe-9aa597183724","name":"layoutSnapshot.svg","type":"layout_snapshot"}],"user_triggered":false},{"id":"6c345e09-4a83-43a4-9d74-c68ee9a427e9","session_id":"d488ad4d-6f40-43a5-8ca3-a504245d3fe6","timestamp":"2025-03-15T11:15:58.049Z","type":"lifecycle_view_controller","lifecycle_view_controller":{"type":"viewWillDisappear","class_name":"UIAlertController"},"attribute":{"thread_name":"com.apple.main-thread","device_name":"iPhone 16 Pro","device_model":"Simulator iPhone17,1","device_manufacturer":"Apple","device_type":"phone","device_is_foldable":false,"device_is_physical":false,"device_density_dpi":480,"device_width_px":1206,"device_height_px":2622,"device_density":3,"device_locale":"en_IN","os_name":"iOS","os_version":"18.3.1","platform":"ios","network_type":"wifi","network_generation":"unknown","network_provider":"unknown","installation_id":"98aa4d46-a856-45a9-b521-f4566532b572","user_id":"test_user_ios","device_cpu_arch":"arm64e","app_version":"1.0.0","app_build":"2","measure_sdk_version":"0.0.1","device_low_power_mode":false,"app_unique_id":"sh.measure.DemoApp"},"user_triggered":false},{"id":"f70fb79f-a938-475e-aa52-b0433f0d90e6","session_id":"d488ad4d-6f40-43a5-8ca3-a504245d3fe6","timestamp":"2025-03-15T11:15:58.629Z","type":"lifecycle_view_controller","lifecycle_view_controller":{"type":"viewDidDisappear","class_name":"UIAlertController"},"attribute":{"thread_name":"com.apple.main-thread","device_name":"iPhone 16 Pro","device_model":"Simulator iPhone17,1","device_manufacturer":"Apple","device_type":"phone","device_is_foldable":false,"device_is_physical":false,"device_density_dpi":480,"device_width_px":1206,"device_height_px":2622,"device_density":3,"device_locale":"en_IN","os_name":"iOS","os_version":"18.3.1","platform":"ios","network_type":"wifi","network_generation":"unknown","network_provider":"unknown","installation_id":"98aa4d46-a856-45a9-b521-f4566532b572","user_id":"test_user_ios","device_cpu_arch":"arm64e","app_version":"1.0.0","app_build":"2","measure_sdk_version":"0.0.1","device_low_power_mode":false,"app_unique_id":"sh.measure.DemoApp"},"user_triggered":false},{"id":"d1a232e3-6b11-4ac8-9533-404d8949058a","session_id":"d488ad4d-6f40-43a5-8ca3-a504245d3fe6","timestamp":"2025-03-15T11:15:59.099Z","type":"memory_usage_absolute","memory_usage_absolute":{"interval":2000,"used_memory":28594,"max_memory":25165824},"attribute":{"thread_name":"com.apple.main-thread","device_name":"iPhone 16 Pro","device_model":"Simulator iPhone17,1","device_manufacturer":"Apple","device_type":"phone","device_is_foldable":false,"device_is_physical":false,"device_density_dpi":480,"device_width_px":1206,"device_height_px":2622,"device_density":3,"device_locale":"en_IN","os_name":"iOS","os_version":"18.3.1","platform":"ios","network_type":"wifi","network_generation":"unknown","network_provider":"unknown","installation_id":"98aa4d46-a856-45a9-b521-f4566532b572","user_id":"test_user_ios","device_cpu_arch":"arm64e","app_version":"1.0.0","app_build":"2","measure_sdk_version":"0.0.1","device_low_power_mode":false,"app_unique_id":"sh.measure.DemoApp"},"user_triggered":false},{"id":"3d3db841-fe24-4d3b-a2fe-07d7d549cbcd","session_id":"d488ad4d-6f40-43a5-8ca3-a504245d3fe6","timestamp":"2025-03-15T11:15:59.937Z","type":"lifecycle_app","lifecycle_app":{"type":"background"},"attribute":{"thread_name":"com.apple.main-thread","device_name":"iPhone 16 Pro","device_model":"Simulator iPhone17,1","device_manufacturer":"Apple","device_type":"phone","device_is_foldable":false,"device_is_physical":false,"device_density_dpi":480,"device_width_px":1206,"device_height_px":2622,"device_density":3,"device_locale":"en_IN","os_name":"iOS","os_version":"18.3.1","platform":"ios","network_type":"wifi","network_generation":"unknown","network_provider":"unknown","installation_id":"98aa4d46-a856-45a9-b521-f4566532b572","user_id":"test_user_ios","device_cpu_arch":"arm64e","app_version":"1.0.0","app_build":"2","measure_sdk_version":"0.0.1","device_low_power_mode":false,"app_unique_id":"sh.measure.DemoApp"},"user_triggered":false},{"id":"8042f6d7-3605-4d64-8102-c67ce2fe5880","session_id":"d488ad4d-6f40-43a5-8ca3-a504245d3fe6","timestamp":"2025-03-15T11:16:00.358Z","type":"lifecycle_app","lifecycle_app":{"type":"foreground"},"attribute":{"thread_name":"com.apple.main-thread","device_name":"iPhone 16 Pro","device_model":"Simulator iPhone17,1","device_manufacturer":"Apple","device_type":"phone","device_is_foldable":false,"device_is_physical":false,"device_density_dpi":480,"device_width_px":1206,"device_height_px":2622,"device_density":3,"device_locale":"en_IN","os_name":"iOS","os_version":"18.3.1","platform":"ios","network_type":"wifi","network_generation":"unknown","network_provider":"unknown","installation_id":"98aa4d46-a856-45a9-b521-f4566532b572","user_id":"test_user_ios","device_cpu_arch":"arm64e","app_version":"1.0.0","app_build":"2","measure_sdk_version":"0.0.1","device_low_power_mode":false,"app_unique_id":"sh.measure.DemoApp"},"user_triggered":false},{"id":"69cd980b-6916-4218-b3f5-a4d971284135","session_id":"d488ad4d-6f40-43a5-8ca3-a504245d3fe6","timestamp":"2025-03-15T11:16:00.666Z","type":"hot_launch","hot_launch":{"app_visible_uptime":124405390,"on_next_draw_uptime":124405693,"launched_activity":"UINavigationController","has_saved_state":false,"intent_data":""},"attribute":{"thread_name":"com.apple.main-thread","device_name":"iPhone 16 Pro","device_model":"Simulator iPhone17,1","device_manufacturer":"Apple","device_type":"phone","device_is_foldable":false,"device_is_physical":false,"device_density_dpi":480,"device_width_px":1206,"device_height_px":2622,"device_density":3,"device_locale":"en_IN","os_name":"iOS","os_version":"18.3.1","platform":"ios","network_type":"wifi","network_generation":"unknown","network_provider":"unknown","installation_id":"98aa4d46-a856-45a9-b521-f4566532b572","user_id":"test_user_ios","device_cpu_arch":"arm64e","app_version":"1.0.0","app_build":"2","measure_sdk_version":"0.0.1","device_low_power_mode":false,"app_unique_id":"sh.measure.DemoApp"},"user_triggered":false},{"id":"656ebe42-bbd3-471e-8120-0c77b6a06e3b","session_id":"d488ad4d-6f40-43a5-8ca3-a504245d3fe6","timestamp":"2025-03-15T11:16:01.827Z","type":"gesture_click","gesture_click":{"target":"UIButtonLabel","target_id":"","width":159,"height":24,"x":87.66666,"y":85.66666,"touch_down_time":124406743,"touch_up_time":124406851},"attribute":{"thread_name":"com.apple.main-thread","device_name":"iPhone 16 Pro","device_model":"Simulator iPhone17,1","device_manufacturer":"Apple","device_type":"phone","device_is_foldable":false,"device_is_physical":false,"device_density_dpi":480,"device_width_px":1206,"device_height_px":2622,"device_density":3,"device_locale":"en_IN","os_name":"iOS","os_version":"18.3.1","platform":"ios","network_type":"wifi","network_generation":"unknown","network_provider":"unknown","installation_id":"98aa4d46-a856-45a9-b521-f4566532b572","user_id":"test_user_ios","device_cpu_arch":"arm64e","app_version":"1.0.0","app_build":"2","measure_sdk_version":"0.0.1","device_low_power_mode":false,"app_unique_id":"sh.measure.DemoApp"},"attachments":[{"id":"bf88acf1-a610-4566-8504-79820a249078","name":"layoutSnapshot.svg","type":"layout_snapshot"}],"user_triggered":false},{"id":"f15df7f2-d8e3-4a37-b2b1-a30808d65ec7","session_id":"d488ad4d-6f40-43a5-8ca3-a504245d3fe6","timestamp":"2025-03-15T11:16:01.841Z","type":"lifecycle_view_controller","lifecycle_view_controller":{"type":"viewWillDisappear","class_name":"ControlsViewController"},"attribute":{"thread_name":"com.apple.main-thread","device_name":"iPhone 16 Pro","device_model":"Simulator iPhone17,1","device_manufacturer":"Apple","device_type":"phone","device_is_foldable":false,"device_is_physical":false,"device_density_dpi":480,"device_width_px":1206,"device_height_px":2622,"device_density":3,"device_locale":"en_IN","os_name":"iOS","os_version":"18.3.1","platform":"ios","network_type":"wifi","network_generation":"unknown","network_provider":"unknown","installation_id":"98aa4d46-a856-45a9-b521-f4566532b572","user_id":"test_user_ios","device_cpu_arch":"arm64e","app_version":"1.0.0","app_build":"2","measure_sdk_version":"0.0.1","device_low_power_mode":false,"app_unique_id":"sh.measure.DemoApp"},"user_triggered":false},{"id":"cf7f662d-5598-4e98-9770-85c40c109bb9","session_id":"d488ad4d-6f40-43a5-8ca3-a504245d3fe6","timestamp":"2025-03-15T11:16:01.845Z","type":"lifecycle_view_controller","lifecycle_view_controller":{"type":"viewWillAppear","class_name":"ViewController"},"attribute":{"thread_name":"com.apple.main-thread","device_name":"iPhone 16 Pro","device_model":"Simulator iPhone17,1","device_manufacturer":"Apple","device_type":"phone","device_is_foldable":false,"device_is_physical":false,"device_density_dpi":480,"device_width_px":1206,"device_height_px":2622,"device_density":3,"device_locale":"en_IN","os_name":"iOS","os_version":"18.3.1","platform":"ios","network_type":"wifi","network_generation":"unknown","network_provider":"unknown","installation_id":"98aa4d46-a856-45a9-b521-f4566532b572","user_id":"test_user_ios","device_cpu_arch":"arm64e","app_version":"1.0.0","app_build":"2","measure_sdk_version":"0.0.1","device_low_power_mode":false,"app_unique_id":"sh.measure.DemoApp"},"user_triggered":false},{"id":"7ff7d9e5-cb73-4ede-81f4-b16ba33cd343","session_id":"d488ad4d-6f40-43a5-8ca3-a504245d3fe6","timestamp":"2025-03-15T11:16:02.364Z","type":"lifecycle_view_controller","lifecycle_view_controller":{"type":"viewDidDisappear","class_name":"ControlsViewController"},"attribute":{"thread_name":"com.apple.main-thread","device_name":"iPhone 16 Pro","device_model":"Simulator iPhone17,1","device_manufacturer":"Apple","device_type":"phone","device_is_foldable":false,"device_is_physical":false,"device_density_dpi":480,"device_width_px":1206,"device_height_px":2622,"device_density":3,"device_locale":"en_IN","os_name":"iOS","os_version":"18.3.1","platform":"ios","network_type":"wifi","network_generation":"unknown","network_provider":"unknown","installation_id":"98aa4d46-a856-45a9-b521-f4566532b572","user_id":"test_user_ios","device_cpu_arch":"arm64e","app_version":"1.0.0","app_build":"2","measure_sdk_version":"0.0.1","device_low_power_mode":false,"app_unique_id":"sh.measure.DemoApp"},"user_triggered":false},{"id":"2f8a14de-ee07-4071-b72e-b5074bbe8fbc","session_id":"d488ad4d-6f40-43a5-8ca3-a504245d3fe6","timestamp":"2025-03-15T11:16:02.372Z","type":"lifecycle_view_controller","lifecycle_view_controller":{"type":"viewDidAppear","class_name":"ViewController"},"attribute":{"thread_name":"com.apple.main-thread","device_name":"iPhone 16 Pro","device_model":"Simulator iPhone17,1","device_manufacturer":"Apple","device_type":"phone","device_is_foldable":false,"device_is_physical":false,"device_density_dpi":480,"device_width_px":1206,"device_height_px":2622,"device_density":3,"device_locale":"en_IN","os_name":"iOS","os_version":"18.3.1","platform":"ios","network_type":"wifi","network_generation":"unknown","network_provider":"unknown","installation_id":"98aa4d46-a856-45a9-b521-f4566532b572","user_id":"test_user_ios","device_cpu_arch":"arm64e","app_version":"1.0.0","app_build":"2","measure_sdk_version":"0.0.1","device_low_power_mode":false,"app_unique_id":"sh.measure.DemoApp"},"user_triggered":false},{"id":"86f57db9-93c6-4c8a-b51d-4f87e3680913","session_id":"d488ad4d-6f40-43a5-8ca3-a504245d3fe6","timestamp":"2025-03-15T11:16:02.377Z","type":"screen_view","screen_view":{"name":"Home"},"attribute":{"thread_name":"com.apple.main-thread","device_name":"iPhone 16 Pro","device_model":"Simulator iPhone17,1","device_manufacturer":"Apple","device_type":"phone","device_is_foldable":false,"device_is_physical":false,"device_density_dpi":480,"device_width_px":1206,"device_height_px":2622,"device_density":3,"device_locale":"en_IN","os_name":"iOS","os_version":"18.3.1","platform":"ios","network_type":"wifi","network_generation":"unknown","network_provider":"unknown","installation_id":"98aa4d46-a856-45a9-b521-f4566532b572","user_id":"test_user_ios","device_cpu_arch":"arm64e","app_version":"1.0.0","app_build":"2","measure_sdk_version":"0.0.1","device_low_power_mode":false,"app_unique_id":"sh.measure.DemoApp"},"user_triggered":true},{"id":"a95dadc9-f57a-4462-b7e4-c6055f4e2a2b","session_id":"d488ad4d-6f40-43a5-8ca3-a504245d3fe6","timestamp":"2025-03-15T11:16:02.385Z","type":"memory_usage_absolute","memory_usage_absolute":{"interval":2000,"used_memory":32978,"max_memory":25165824},"attribute":{"thread_name":"com.apple.main-thread","device_name":"iPhone 16 Pro","device_model":"Simulator iPhone17,1","device_manufacturer":"Apple","device_type":"phone","device_is_foldable":false,"device_is_physical":false,"device_density_dpi":480,"device_width_px":1206,"device_height_px":2622,"device_density":3,"device_locale":"en_IN","os_name":"iOS","os_version":"18.3.1","platform":"ios","network_type":"wifi","network_generation":"unknown","network_provider":"unknown","installation_id":"98aa4d46-a856-45a9-b521-f4566532b572","user_id":"test_user_ios","device_cpu_arch":"arm64e","app_version":"1.0.0","app_build":"2","measure_sdk_version":"0.0.1","device_low_power_mode":false,"app_unique_id":"sh.measure.DemoApp"},"user_triggered":false},{"id":"0fecf143-f465-4461-a28a-66f4a388476e","session_id":"d488ad4d-6f40-43a5-8ca3-a504245d3fe6","timestamp":"2025-03-15T11:16:02.476Z","type":"gesture_click","gesture_click":{"target":"UIButtonLabel","target_id":"","width":104,"height":18,"x":109.33333,"y":204.66666,"touch_down_time":124407417,"touch_up_time":124407502},"attribute":{"thread_name":"com.apple.main-thread","device_name":"iPhone 16 Pro","device_model":"Simulator iPhone17,1","device_manufacturer":"Apple","device_type":"phone","device_is_foldable":false,"device_is_physical":false,"device_density_dpi":480,"device_width_px":1206,"device_height_px":2622,"device_density":3,"device_locale":"en_IN","os_name":"iOS","os_version":"18.3.1","platform":"ios","network_type":"wifi","network_generation":"unknown","network_provider":"unknown","installation_id":"98aa4d46-a856-45a9-b521-f4566532b572","user_id":"test_user_ios","device_cpu_arch":"arm64e","app_version":"1.0.0","app_build":"2","measure_sdk_version":"0.0.1","device_low_power_mode":false,"app_unique_id":"sh.measure.DemoApp"},"user_triggered":false},{"id":"3143052f-37b9-4b50-b33b-ed3b08e33fa3","session_id":"d488ad4d-6f40-43a5-8ca3-a504245d3fe6","timestamp":"2025-03-15T11:16:02.483Z","type":"lifecycle_view_controller","lifecycle_view_controller":{"type":"viewDidLoad","class_name":"ObjcDetailViewController"},"attribute":{"thread_name":"com.apple.main-thread","device_name":"iPhone 16 Pro","device_model":"Simulator iPhone17,1","device_manufacturer":"Apple","device_type":"phone","device_is_foldable":false,"device_is_physical":false,"device_density_dpi":480,"device_width_px":1206,"device_height_px":2622,"device_density":3,"device_locale":"en_IN","os_name":"iOS","os_version":"18.3.1","platform":"ios","network_type":"wifi","network_generation":"unknown","network_provider":"unknown","installation_id":"98aa4d46-a856-45a9-b521-f4566532b572","user_id":"test_user_ios","device_cpu_arch":"arm64e","app_version":"1.0.0","app_build":"2","measure_sdk_version":"0.0.1","device_low_power_mode":false,"app_unique_id":"sh.measure.DemoApp"},"user_triggered":false},{"id":"8a91718b-8b64-40b2-8a86-aa70f3f14a0d","session_id":"d488ad4d-6f40-43a5-8ca3-a504245d3fe6","timestamp":"2025-03-15T11:16:02.489Z","type":"custom","custom":{"name":"event-name"},"attribute":{"thread_name":"com.apple.main-thread","device_name":"iPhone 16 Pro","device_model":"Simulator iPhone17,1","device_manufacturer":"Apple","device_type":"phone","device_is_foldable":false,"device_is_physical":false,"device_density_dpi":480,"device_width_px":1206,"device_height_px":2622,"device_density":3,"device_locale":"en_IN","os_name":"iOS","os_version":"18.3.1","platform":"ios","network_type":"wifi","network_generation":"unknown","network_provider":"unknown","installation_id":"98aa4d46-a856-45a9-b521-f4566532b572","user_id":"test_user_ios","device_cpu_arch":"arm64e","app_version":"1.0.0","app_build":"2","measure_sdk_version":"0.0.1","device_low_power_mode":false,"app_unique_id":"sh.measure.DemoApp"},"user_defined_attribute":{"paid_user":true,"latitude":30.2661403415387,"user_name":"Alice","credit_balance":1000},"user_triggered":true},{"id":"47827f8d-cf7a-43c8-a9ac-7b739c1d04e4","session_id":"d488ad4d-6f40-43a5-8ca3-a504245d3fe6","timestamp":"2025-03-15T11:16:02.494Z","type":"screen_view","screen_view":{"name":"ObjcViewController"},"attribute":{"thread_name":"com.apple.main-thread","device_name":"iPhone 16 Pro","device_model":"Simulator iPhone17,1","device_manufacturer":"Apple","device_type":"phone","device_is_foldable":false,"device_is_physical":false,"device_density_dpi":480,"device_width_px":1206,"device_height_px":2622,"device_density":3,"device_locale":"en_IN","os_name":"iOS","os_version":"18.3.1","platform":"ios","network_type":"wifi","network_generation":"unknown","network_provider":"unknown","installation_id":"98aa4d46-a856-45a9-b521-f4566532b572","user_id":"test_user_ios","device_cpu_arch":"arm64e","app_version":"1.0.0","app_build":"2","measure_sdk_version":"0.0.1","device_low_power_mode":false,"app_unique_id":"sh.measure.DemoApp"},"user_triggered":true},{"id":"7235ff47-6722-42dc-94c3-7d957d4ed5cf","session_id":"d488ad4d-6f40-43a5-8ca3-a504245d3fe6","timestamp":"2025-03-15T11:16:02.497Z","type":"lifecycle_view_controller","lifecycle_view_controller":{"type":"viewWillDisappear","class_name":"ViewController"},"attribute":{"thread_name":"com.apple.main-thread","device_name":"iPhone 16 Pro","device_model":"Simulator iPhone17,1","device_manufacturer":"Apple","device_type":"phone","device_is_foldable":false,"device_is_physical":false,"device_density_dpi":480,"device_width_px":1206,"device_height_px":2622,"device_density":3,"device_locale":"en_IN","os_name":"iOS","os_version":"18.3.1","platform":"ios","network_type":"wifi","network_generation":"unknown","network_provider":"unknown","installation_id":"98aa4d46-a856-45a9-b521-f4566532b572","user_id":"test_user_ios","device_cpu_arch":"arm64e","app_version":"1.0.0","app_build":"2","measure_sdk_version":"0.0.1","device_low_power_mode":false,"app_unique_id":"sh.measure.DemoApp"},"user_triggered":false},{"id":"c873f112-42eb-4e31-ac90-fa99554acd66","session_id":"d488ad4d-6f40-43a5-8ca3-a504245d3fe6","timestamp":"2025-03-15T11:16:02.501Z","type":"lifecycle_view_controller","lifecycle_view_controller":{"type":"viewWillAppear","class_name":"ObjcDetailViewController"},"attribute":{"thread_name":"com.apple.main-thread","device_name":"iPhone 16 Pro","device_model":"Simulator iPhone17,1","device_manufacturer":"Apple","device_type":"phone","device_is_foldable":false,"device_is_physical":false,"device_density_dpi":480,"device_width_px":1206,"device_height_px":2622,"device_density":3,"device_locale":"en_IN","os_name":"iOS","os_version":"18.3.1","platform":"ios","network_type":"wifi","network_generation":"unknown","network_provider":"unknown","installation_id":"98aa4d46-a856-45a9-b521-f4566532b572","user_id":"test_user_ios","device_cpu_arch":"arm64e","app_version":"1.0.0","app_build":"2","measure_sdk_version":"0.0.1","device_low_power_mode":false,"app_unique_id":"sh.measure.DemoApp"},"user_triggered":false},{"id":"8431f56f-9493-4e8c-8a2c-817832f0ef59","session_id":"d488ad4d-6f40-43a5-8ca3-a504245d3fe6","timestamp":"2025-03-15T11:16:03.027Z","type":"lifecycle_view_controller","lifecycle_view_controller":{"type":"viewDidDisappear","class_name":"ViewController"},"attribute":{"thread_name":"com.apple.main-thread","device_name":"iPhone 16 Pro","device_model":"Simulator iPhone17,1","device_manufacturer":"Apple","device_type":"phone","device_is_foldable":false,"device_is_physical":false,"device_density_dpi":480,"device_width_px":1206,"device_height_px":2622,"device_density":3,"device_locale":"en_IN","os_name":"iOS","os_version":"18.3.1","platform":"ios","network_type":"wifi","network_generation":"unknown","network_provider":"unknown","installation_id":"98aa4d46-a856-45a9-b521-f4566532b572","user_id":"test_user_ios","device_cpu_arch":"arm64e","app_version":"1.0.0","app_build":"2","measure_sdk_version":"0.0.1","device_low_power_mode":false,"app_unique_id":"sh.measure.DemoApp"},"user_triggered":false},{"id":"afb255c6-e0fc-447a-8fda-6a8e951e06d9","session_id":"d488ad4d-6f40-43a5-8ca3-a504245d3fe6","timestamp":"2025-03-15T11:16:03.036Z","type":"custom","custom":{"name":"custom_event"},"attribute":{"thread_name":"com.apple.main-thread","device_name":"iPhone 16 Pro","device_model":"Simulator iPhone17,1","device_manufacturer":"Apple","device_type":"phone","device_is_foldable":false,"device_is_physical":false,"device_density_dpi":480,"device_width_px":1206,"device_height_px":2622,"device_density":3,"device_locale":"en_IN","os_name":"iOS","os_version":"18.3.1","platform":"ios","network_type":"wifi","network_generation":"unknown","network_provider":"unknown","installation_id":"98aa4d46-a856-45a9-b521-f4566532b572","user_id":"test_user_ios","device_cpu_arch":"arm64e","app_version":"1.0.0","app_build":"2","measure_sdk_version":"0.0.1","device_low_power_mode":false,"app_unique_id":"sh.measure.DemoApp"},"user_defined_attribute":{"credit_balance":1000,"latitude":30.2661403415387,"user_name":"Alice","paid_user":true},"user_triggered":true},{"id":"fec4a7c1-304e-48ed-aa35-5fca7a2a459f","session_id":"d488ad4d-6f40-43a5-8ca3-a504245d3fe6","timestamp":"2025-03-15T11:16:03.041Z","type":"lifecycle_view_controller","lifecycle_view_controller":{"type":"viewDidAppear","class_name":"ObjcDetailViewController"},"attribute":{"thread_name":"com.apple.main-thread","device_name":"iPhone 16 Pro","device_model":"Simulator iPhone17,1","device_manufacturer":"Apple","device_type":"phone","device_is_foldable":false,"device_is_physical":false,"device_density_dpi":480,"device_width_px":1206,"device_height_px":2622,"device_density":3,"device_locale":"en_IN","os_name":"iOS","os_version":"18.3.1","platform":"ios","network_type":"wifi","network_generation":"unknown","network_provider":"unknown","installation_id":"98aa4d46-a856-45a9-b521-f4566532b572","user_id":"test_user_ios","device_cpu_arch":"arm64e","app_version":"1.0.0","app_build":"2","measure_sdk_version":"0.0.1","device_low_power_mode":false,"app_unique_id":"sh.measure.DemoApp"},"user_triggered":false},{"id":"051903b4-5199-4535-aafb-581002e4f9fb","session_id":"d488ad4d-6f40-43a5-8ca3-a504245d3fe6","timestamp":"2025-03-15T11:16:03.364Z","type":"cpu_usage","cpu_usage":{"num_cores":14,"clock_speed":4500000000,"start_time":0,"uptime":0,"utime":0,"cutime":0,"cstime":0,"stime":0,"interval":3000,"percentage_usage":7.3999999999999995},"attribute":{"thread_name":"com.apple.main-thread","device_name":"iPhone 16 Pro","device_model":"Simulator iPhone17,1","device_manufacturer":"Apple","device_type":"phone","device_is_foldable":false,"device_is_physical":false,"device_density_dpi":480,"device_width_px":1206,"device_height_px":2622,"device_density":3,"device_locale":"en_IN","os_name":"iOS","os_version":"18.3.1","platform":"ios","network_type":"wifi","network_generation":"unknown","network_provider":"unknown","installation_id":"98aa4d46-a856-45a9-b521-f4566532b572","user_id":"test_user_ios","device_cpu_arch":"arm64e","app_version":"1.0.0","app_build":"2","measure_sdk_version":"0.0.1","device_low_power_mode":false,"app_unique_id":"sh.measure.DemoApp"},"user_triggered":false},{"id":"67ddc95d-e9aa-46dd-8e8b-e6e0124a0085","session_id":"d488ad4d-6f40-43a5-8ca3-a504245d3fe6","timestamp":"2025-03-15T11:16:03.453Z","type":"gesture_click","gesture_click":{"target":"UIButton","target_id":"","width":173,"height":84,"x":279.66666,"y":135.0,"touch_down_time":124408352,"touch_up_time":124408478},"attribute":{"thread_name":"com.apple.main-thread","device_name":"iPhone 16 Pro","device_model":"Simulator iPhone17,1","device_manufacturer":"Apple","device_type":"phone","device_is_foldable":false,"device_is_physical":false,"device_density_dpi":480,"device_width_px":1206,"device_height_px":2622,"device_density":3,"device_locale":"en_IN","os_name":"iOS","os_version":"18.3.1","platform":"ios","network_type":"wifi","network_generation":"unknown","network_provider":"unknown","installation_id":"98aa4d46-a856-45a9-b521-f4566532b572","user_id":"test_user_ios","device_cpu_arch":"arm64e","app_version":"1.0.0","app_build":"2","measure_sdk_version":"0.0.1","device_low_power_mode":false,"app_unique_id":"sh.measure.DemoApp"},"attachments":[{"id":"8b4cfb39-ee2f-4cb1-8462-de0fc005e915","name":"layoutSnapshot.svg","type":"layout_snapshot"}],"user_triggered":false},{"id":"3afaafee-8aa7-42ae-8d0f-414e934eb383","session_id":"d488ad4d-6f40-43a5-8ca3-a504245d3fe6","timestamp":"2025-03-15T11:16:03.465Z","type":"lifecycle_view_controller","lifecycle_view_controller":{"type":"viewDidLoad","class_name":"CollectionViewController"},"attribute":{"thread_name":"com.apple.main-thread","device_name":"iPhone 16 Pro","device_model":"Simulator iPhone17,1","device_manufacturer":"Apple","device_type":"phone","device_is_foldable":false,"device_is_physical":false,"device_density_dpi":480,"device_width_px":1206,"device_height_px":2622,"device_density":3,"device_locale":"en_IN","os_name":"iOS","os_version":"18.3.1","platform":"ios","network_type":"wifi","network_generation":"unknown","network_provider":"unknown","installation_id":"98aa4d46-a856-45a9-b521-f4566532b572","user_id":"test_user_ios","device_cpu_arch":"arm64e","app_version":"1.0.0","app_build":"2","measure_sdk_version":"0.0.1","device_low_power_mode":false,"app_unique_id":"sh.measure.DemoApp"},"user_triggered":false},{"id":"4e158478-419a-4f65-8ddd-bd5dcb88ee36","session_id":"d488ad4d-6f40-43a5-8ca3-a504245d3fe6","timestamp":"2025-03-15T11:16:03.472Z","type":"lifecycle_view_controller","lifecycle_view_controller":{"type":"viewWillDisappear","class_name":"ObjcDetailViewController"},"attribute":{"thread_name":"com.apple.main-thread","device_name":"iPhone 16 Pro","device_model":"Simulator iPhone17,1","device_manufacturer":"Apple","device_type":"phone","device_is_foldable":false,"device_is_physical":false,"device_density_dpi":480,"device_width_px":1206,"device_height_px":2622,"device_density":3,"device_locale":"en_IN","os_name":"iOS","os_version":"18.3.1","platform":"ios","network_type":"wifi","network_generation":"unknown","network_provider":"unknown","installation_id":"98aa4d46-a856-45a9-b521-f4566532b572","user_id":"test_user_ios","device_cpu_arch":"arm64e","app_version":"1.0.0","app_build":"2","measure_sdk_version":"0.0.1","device_low_power_mode":false,"app_unique_id":"sh.measure.DemoApp"},"user_triggered":false},{"id":"d87358aa-e70b-4f73-8564-a11de522a1a8","session_id":"d488ad4d-6f40-43a5-8ca3-a504245d3fe6","timestamp":"2025-03-15T11:16:03.475Z","type":"lifecycle_view_controller","lifecycle_view_controller":{"type":"viewWillAppear","class_name":"CollectionViewController"},"attribute":{"thread_name":"com.apple.main-thread","device_name":"iPhone 16 Pro","device_model":"Simulator iPhone17,1","device_manufacturer":"Apple","device_type":"phone","device_is_foldable":false,"device_is_physical":false,"device_density_dpi":480,"device_width_px":1206,"device_height_px":2622,"device_density":3,"device_locale":"en_IN","os_name":"iOS","os_version":"18.3.1","platform":"ios","network_type":"wifi","network_generation":"unknown","network_provider":"unknown","installation_id":"98aa4d46-a856-45a9-b521-f4566532b572","user_id":"test_user_ios","device_cpu_arch":"arm64e","app_version":"1.0.0","app_build":"2","measure_sdk_version":"0.0.1","device_low_power_mode":false,"app_unique_id":"sh.measure.DemoApp"},"user_triggered":false},{"id":"2c1911ea-a707-4b01-947b-07ce03cedc92","session_id":"d488ad4d-6f40-43a5-8ca3-a504245d3fe6","timestamp":"2025-03-15T11:16:04.006Z","type":"lifecycle_view_controller","lifecycle_view_controller":{"type":"viewDidDisappear","class_name":"ObjcDetailViewController"},"attribute":{"thread_name":"com.apple.main-thread","device_name":"iPhone 16 Pro","device_model":"Simulator iPhone17,1","device_manufacturer":"Apple","device_type":"phone","device_is_foldable":false,"device_is_physical":false,"device_density_dpi":480,"device_width_px":1206,"device_height_px":2622,"device_density":3,"device_locale":"en_IN","os_name":"iOS","os_version":"18.3.1","platform":"ios","network_type":"wifi","network_generation":"unknown","network_provider":"unknown","installation_id":"98aa4d46-a856-45a9-b521-f4566532b572","user_id":"test_user_ios","device_cpu_arch":"arm64e","app_version":"1.0.0","app_build":"2","measure_sdk_version":"0.0.1","device_low_power_mode":false,"app_unique_id":"sh.measure.DemoApp"},"user_triggered":false},{"id":"d3465a53-556d-48b4-9c72-6b870c5ebbec","session_id":"d488ad4d-6f40-43a5-8ca3-a504245d3fe6","timestamp":"2025-03-15T11:16:04.016Z","type":"lifecycle_view_controller","lifecycle_view_controller":{"type":"viewDidAppear","class_name":"CollectionViewController"},"attribute":{"thread_name":"com.apple.main-thread","device_name":"iPhone 16 Pro","device_model":"Simulator iPhone17,1","device_manufacturer":"Apple","device_type":"phone","device_is_foldable":false,"device_is_physical":false,"device_density_dpi":480,"device_width_px":1206,"device_height_px":2622,"device_density":3,"device_locale":"en_IN","os_name":"iOS","os_version":"18.3.1","platform":"ios","network_type":"wifi","network_generation":"unknown","network_provider":"unknown","installation_id":"98aa4d46-a856-45a9-b521-f4566532b572","user_id":"test_user_ios","device_cpu_arch":"arm64e","app_version":"1.0.0","app_build":"2","measure_sdk_version":"0.0.1","device_low_power_mode":false,"app_unique_id":"sh.measure.DemoApp"},"user_triggered":false},{"id":"3729fed5-6087-44c4-aee8-edb96980cd83","session_id":"d488ad4d-6f40-43a5-8ca3-a504245d3fe6","timestamp":"2025-03-15T11:16:04.210Z","type":"gesture_scroll","gesture_scroll":{"target":"UICollectionView","target_id":"","x":215.0,"y":590.6666,"end_x":215.0,"end_y":306.3333,"direction":"up","touch_down_time":124409051,"touch_up_time":124409234},"attribute":{"thread_name":"com.apple.main-thread","device_name":"iPhone 16 Pro","device_model":"Simulator iPhone17,1","device_manufacturer":"Apple","device_type":"phone","device_is_foldable":false,"device_is_physical":false,"device_density_dpi":480,"device_width_px":1206,"device_height_px":2622,"device_density":3,"device_locale":"en_IN","os_name":"iOS","os_version":"18.3.1","platform":"ios","network_type":"wifi","network_generation":"unknown","network_provider":"unknown","installation_id":"98aa4d46-a856-45a9-b521-f4566532b572","user_id":"test_user_ios","device_cpu_arch":"arm64e","app_version":"1.0.0","app_build":"2","measure_sdk_version":"0.0.1","device_low_power_mode":false,"app_unique_id":"sh.measure.DemoApp"},"attachments":[{"id":"6122d15f-d15a-4147-8d6f-482c65c6cbfa","name":"layoutSnapshot.svg","type":"layout_snapshot"}],"user_triggered":false},{"id":"a0fef35a-ea83-44da-a87b-7b092f2b46cb","session_id":"d488ad4d-6f40-43a5-8ca3-a504245d3fe6","timestamp":"2025-03-15T11:16:05.258Z","type":"memory_usage_absolute","memory_usage_absolute":{"interval":2000,"used_memory":34754,"max_memory":25165824},"attribute":{"thread_name":"com.apple.main-thread","device_name":"iPhone 16 Pro","device_model":"Simulator iPhone17,1","device_manufacturer":"Apple","device_type":"phone","device_is_foldable":false,"device_is_physical":false,"device_density_dpi":480,"device_width_px":1206,"device_height_px":2622,"device_density":3,"device_locale":"en_IN","os_name":"iOS","os_version":"18.3.1","platform":"ios","network_type":"wifi","network_generation":"unknown","network_provider":"unknown","installation_id":"98aa4d46-a856-45a9-b521-f4566532b572","user_id":"test_user_ios","device_cpu_arch":"arm64e","app_version":"1.0.0","app_build":"2","measure_sdk_version":"0.0.1","device_low_power_mode":false,"app_unique_id":"sh.measure.DemoApp"},"user_triggered":false},{"id":"592630f5-a9f5-4a50-967f-0b31db4bb3b8","session_id":"d488ad4d-6f40-43a5-8ca3-a504245d3fe6","timestamp":"2025-03-15T11:16:06.364Z","type":"cpu_usage","cpu_usage":{"num_cores":14,"clock_speed":4500000000,"start_time":0,"uptime":0,"utime":0,"cutime":0,"cstime":0,"stime":0,"interval":3000,"percentage_usage":0.8},"attribute":{"thread_name":"com.apple.main-thread","device_name":"iPhone 16 Pro","device_model":"Simulator iPhone17,1","device_manufacturer":"Apple","device_type":"phone","device_is_foldable":false,"device_is_physical":false,"device_density_dpi":480,"device_width_px":1206,"device_height_px":2622,"device_density":3,"device_locale":"en_IN","os_name":"iOS","os_version":"18.3.1","platform":"ios","network_type":"wifi","network_generation":"unknown","network_provider":"unknown","installation_id":"98aa4d46-a856-45a9-b521-f4566532b572","user_id":"test_user_ios","device_cpu_arch":"arm64e","app_version":"1.0.0","app_build":"2","measure_sdk_version":"0.0.1","device_low_power_mode":false,"app_unique_id":"sh.measure.DemoApp"},"user_triggered":false},{"id":"7b9be55c-14eb-45bb-bcb4-e687d0861d67","session_id":"d488ad4d-6f40-43a5-8ca3-a504245d3fe6","timestamp":"2025-03-15T11:16:06.373Z","type":"memory_usage_absolute","memory_usage_absolute":{"interval":2000,"used_memory":34738,"max_memory":25165824},"attribute":{"thread_name":"com.apple.main-thread","device_name":"iPhone 16 Pro","device_model":"Simulator iPhone17,1","device_manufacturer":"Apple","device_type":"phone","device_is_foldable":false,"device_is_physical":false,"device_density_dpi":480,"device_width_px":1206,"device_height_px":2622,"device_density":3,"device_locale":"en_IN","os_name":"iOS","os_version":"18.3.1","platform":"ios","network_type":"wifi","network_generation":"unknown","network_provider":"unknown","installation_id":"98aa4d46-a856-45a9-b521-f4566532b572","user_id":"test_user_ios","device_cpu_arch":"arm64e","app_version":"1.0.0","app_build":"2","measure_sdk_version":"0.0.1","device_low_power_mode":false,"app_unique_id":"sh.measure.DemoApp"},"user_triggered":false},{"id":"eafc3e4c-b3a9-4d78-982a-00ee4ef48d2e","session_id":"d488ad4d-6f40-43a5-8ca3-a504245d3fe6","timestamp":"2025-03-15T11:16:07.595Z","type":"lifecycle_app","lifecycle_app":{"type":"background"},"attribute":{"thread_name":"com.apple.main-thread","device_name":"iPhone 16 Pro","device_model":"Simulator iPhone17,1","device_manufacturer":"Apple","device_type":"phone","device_is_foldable":false,"device_is_physical":false,"device_density_dpi":480,"device_width_px":1206,"device_height_px":2622,"device_density":3,"device_locale":"en_IN","os_name":"iOS","os_version":"18.3.1","platform":"ios","network_type":"wifi","network_generation":"unknown","network_provider":"unknown","installation_id":"98aa4d46-a856-45a9-b521-f4566532b572","user_id":"test_user_ios","device_cpu_arch":"arm64e","app_version":"1.0.0","app_build":"2","measure_sdk_version":"0.0.1","device_low_power_mode":false,"app_unique_id":"sh.measure.DemoApp"},"user_triggered":false},{"id":"97197a91-9ab8-47d8-98c7-53bd12e3813f","session_id":"6493fe86-af65-4b3a-9ca3-a0fa6e83112f","timestamp":"2025-03-15T11:16:09.256Z","type":"lifecycle_view_controller","lifecycle_view_controller":{"type":"viewDidLoad","class_name":"UINavigationController"},"attribute":{"thread_name":"com.apple.main-thread","device_name":"iPhone 16 Pro","device_model":"Simulator iPhone17,1","device_manufacturer":"Apple","device_type":"phone","device_is_foldable":false,"device_is_physical":false,"device_density_dpi":480,"device_width_px":1206,"device_height_px":2622,"device_density":3,"device_locale":"en_IN","os_name":"iOS","os_version":"18.3.1","platform":"ios","network_type":"wifi","network_generation":"unknown","network_provider":"unknown","installation_id":"98aa4d46-a856-45a9-b521-f4566532b572","user_id":"test_user_ios","device_cpu_arch":"arm64e","app_version":"1.0.0","app_build":"2","measure_sdk_version":"0.0.1","device_low_power_mode":false,"app_unique_id":"sh.measure.DemoApp"},"user_triggered":false},{"id":"238ebacb-035e-45a7-afbe-dddde46b8069","session_id":"6493fe86-af65-4b3a-9ca3-a0fa6e83112f","timestamp":"2025-03-15T11:16:09.262Z","type":"lifecycle_view_controller","lifecycle_view_controller":{"type":"viewWillAppear","class_name":"UINavigationController"},"attribute":{"thread_name":"com.apple.main-thread","device_name":"iPhone 16 Pro","device_model":"Simulator iPhone17,1","device_manufacturer":"Apple","device_type":"phone","device_is_foldable":false,"device_is_physical":false,"device_density_dpi":480,"device_width_px":1206,"device_height_px":2622,"device_density":3,"device_locale":"en_IN","os_name":"iOS","os_version":"18.3.1","platform":"ios","network_type":"wifi","network_generation":"unknown","network_provider":"unknown","installation_id":"98aa4d46-a856-45a9-b521-f4566532b572","user_id":"test_user_ios","device_cpu_arch":"arm64e","app_version":"1.0.0","app_build":"2","measure_sdk_version":"0.0.1","device_low_power_mode":false,"app_unique_id":"sh.measure.DemoApp"},"user_triggered":false},{"id":"4d78a328-69e6-4fef-86fe-a56077ba7761","session_id":"6493fe86-af65-4b3a-9ca3-a0fa6e83112f","timestamp":"2025-03-15T11:16:09.250Z","type":"network_change","network_change":{"network_type":"wifi","network_provider":"unknown","network_generation":"unknown","previous_network_type":"unknown","previous_network_generation":"unknown"},"attribute":{"thread_name":"unknown","device_name":"iPhone 16 Pro","device_model":"Simulator iPhone17,1","device_manufacturer":"Apple","device_type":"phone","device_is_foldable":false,"device_is_physical":false,"device_density_dpi":480,"device_width_px":1206,"device_height_px":2622,"device_density":3,"device_locale":"en_IN","os_name":"iOS","os_version":"18.3.1","platform":"ios","network_type":"wifi","network_generation":"unknown","network_provider":"unknown","installation_id":"98aa4d46-a856-45a9-b521-f4566532b572","user_id":"test_user_ios","device_cpu_arch":"arm64e","app_version":"1.0.0","app_build":"2","measure_sdk_version":"0.0.1","device_low_power_mode":false,"app_unique_id":"sh.measure.DemoApp"},"user_triggered":false},{"id":"a8c1106e-9fe6-4209-9a3c-47d962ee6633","session_id":"6493fe86-af65-4b3a-9ca3-a0fa6e83112f","timestamp":"2025-03-15T11:16:09.269Z","type":"lifecycle_app","lifecycle_app":{"type":"foreground"},"attribute":{"thread_name":"com.apple.main-thread","device_name":"iPhone 16 Pro","device_model":"Simulator iPhone17,1","device_manufacturer":"Apple","device_type":"phone","device_is_foldable":false,"device_is_physical":false,"device_density_dpi":480,"device_width_px":1206,"device_height_px":2622,"device_density":3,"device_locale":"en_IN","os_name":"iOS","os_version":"18.3.1","platform":"ios","network_type":"wifi","network_generation":"unknown","network_provider":"unknown","installation_id":"98aa4d46-a856-45a9-b521-f4566532b572","user_id":"test_user_ios","device_cpu_arch":"arm64e","app_version":"1.0.0","app_build":"2","measure_sdk_version":"0.0.1","device_low_power_mode":false,"app_unique_id":"sh.measure.DemoApp"},"user_triggered":false},{"id":"fc127e2d-eb33-45f7-bb86-2801777cd325","session_id":"6493fe86-af65-4b3a-9ca3-a0fa6e83112f","timestamp":"2025-03-15T11:16:09.274Z","type":"lifecycle_view_controller","lifecycle_view_controller":{"type":"loadView","class_name":"ViewController"},"attribute":{"thread_name":"com.apple.main-thread","device_name":"iPhone 16 Pro","device_model":"Simulator iPhone17,1","device_manufacturer":"Apple","device_type":"phone","device_is_foldable":false,"device_is_physical":false,"device_density_dpi":480,"device_width_px":1206,"device_height_px":2622,"device_density":3,"device_locale":"en_IN","os_name":"iOS","os_version":"18.3.1","platform":"ios","network_type":"wifi","network_generation":"unknown","network_provider":"unknown","installation_id":"98aa4d46-a856-45a9-b521-f4566532b572","user_id":"test_user_ios","device_cpu_arch":"arm64e","app_version":"1.0.0","app_build":"2","measure_sdk_version":"0.0.1","device_low_power_mode":false,"app_unique_id":"sh.measure.DemoApp"},"user_triggered":false},{"id":"4fe8d4e5-1561-429a-bf7a-5973e5206f5e","session_id":"6493fe86-af65-4b3a-9ca3-a0fa6e83112f","timestamp":"2025-03-15T11:16:09.276Z","type":"lifecycle_view_controller","lifecycle_view_controller":{"type":"viewDidLoad","class_name":"ViewController"},"attribute":{"thread_name":"com.apple.main-thread","device_name":"iPhone 16 Pro","device_model":"Simulator iPhone17,1","device_manufacturer":"Apple","device_type":"phone","device_is_foldable":false,"device_is_physical":false,"device_density_dpi":480,"device_width_px":1206,"device_height_px":2622,"device_density":3,"device_locale":"en_IN","os_name":"iOS","os_version":"18.3.1","platform":"ios","network_type":"wifi","network_generation":"unknown","network_provider":"unknown","installation_id":"98aa4d46-a856-45a9-b521-f4566532b572","user_id":"test_user_ios","device_cpu_arch":"arm64e","app_version":"1.0.0","app_build":"2","measure_sdk_version":"0.0.1","device_low_power_mode":false,"app_unique_id":"sh.measure.DemoApp"},"user_triggered":false},{"id":"f889fcd6-88b5-4f7f-96e6-2d82de9cb362","session_id":"6493fe86-af65-4b3a-9ca3-a0fa6e83112f","timestamp":"2025-03-15T11:16:09.281Z","type":"lifecycle_view_controller","lifecycle_view_controller":{"type":"viewWillAppear","class_name":"ViewController"},"attribute":{"thread_name":"com.apple.main-thread","device_name":"iPhone 16 Pro","device_model":"Simulator iPhone17,1","device_manufacturer":"Apple","device_type":"phone","device_is_foldable":false,"device_is_physical":false,"device_density_dpi":480,"device_width_px":1206,"device_height_px":2622,"device_density":3,"device_locale":"en_IN","os_name":"iOS","os_version":"18.3.1","platform":"ios","network_type":"wifi","network_generation":"unknown","network_provider":"unknown","installation_id":"98aa4d46-a856-45a9-b521-f4566532b572","user_id":"test_user_ios","device_cpu_arch":"arm64e","app_version":"1.0.0","app_build":"2","measure_sdk_version":"0.0.1","device_low_power_mode":false,"app_unique_id":"sh.measure.DemoApp"},"user_triggered":false}]}