{"events":[{"id":"98ed4d18-f5ed-4276-9c67-0b5d7ffadccc","session_id":"84d0b81b-beb4-4eeb-b1ab-3bf2575edd26","timestamp":"2025-01-20T13:58:59.366Z","type":"lifecycle_view_controller","lifecycle_view_controller":{"type":"viewDidDisappear","class_name":"UICompatibilityInputViewController"},"attribute":{"thread_name":"com.apple.main-thread","device_name":"iPhone 15 Pro","device_model":"Simulator iPhone 15 Pro","device_manufacturer":"Apple","device_type":"phone","device_is_foldable":false,"device_is_physical":false,"device_density_dpi":480,"device_width_px":1179,"device_height_px":2556,"device_density":3,"device_locale":"en_IN","os_name":"iOS","os_version":"17.4","platform":"ios","network_type":"wifi","network_generation":"unknown","network_provider":"unknown","installation_id":"6e59eb43-73d3-4829-87d1-d4f1a184725b","user_id":"test_user_id","device_cpu_arch":"x86_64","app_version":"7.5.6","app_build":"0","measure_sdk_version":"0.0.1","device_low_power_mode":false,"app_unique_id":"org.wikimedia.wikipedia"},"user_triggered":false},{"id":"fdfd08f6-95c1-4a47-ada0-bcf781630e97","session_id":"84d0b81b-beb4-4eeb-b1ab-3bf2575edd26","timestamp":"2025-01-20T13:58:59.395Z","type":"lifecycle_view_controller","lifecycle_view_controller":{"type":"viewDidDisappear","class_name":"UICompatibilityInputViewController"},"attribute":{"thread_name":"com.apple.main-thread","device_name":"iPhone 15 Pro","device_model":"Simulator iPhone 15 Pro","device_manufacturer":"Apple","device_type":"phone","device_is_foldable":false,"device_is_physical":false,"device_density_dpi":480,"device_width_px":1179,"device_height_px":2556,"device_density":3,"device_locale":"en_IN","os_name":"iOS","os_version":"17.4","platform":"ios","network_type":"wifi","network_generation":"unknown","network_provider":"unknown","installation_id":"6e59eb43-73d3-4829-87d1-d4f1a184725b","user_id":"test_user_id","device_cpu_arch":"x86_64","app_version":"7.5.6","app_build":"0","measure_sdk_version":"0.0.1","device_low_power_mode":false,"app_unique_id":"org.wikimedia.wikipedia"},"user_triggered":false},{"id":"5a4a211c-573a-4488-86ff-560821485377","session_id":"84d0b81b-beb4-4eeb-b1ab-3bf2575edd26","timestamp":"2025-01-20T13:58:59.406Z","type":"lifecycle_view_controller","lifecycle_view_controller":{"type":"viewDidDisappear","class_name":"UISystemInputAssistantViewController"},"attribute":{"thread_name":"com.apple.main-thread","device_name":"iPhone 15 Pro","device_model":"Simulator iPhone 15 Pro","device_manufacturer":"Apple","device_type":"phone","device_is_foldable":false,"device_is_physical":false,"device_density_dpi":480,"device_width_px":1179,"device_height_px":2556,"device_density":3,"device_locale":"en_IN","os_name":"iOS","os_version":"17.4","platform":"ios","network_type":"wifi","network_generation":"unknown","network_provider":"unknown","installation_id":"6e59eb43-73d3-4829-87d1-d4f1a184725b","user_id":"test_user_id","device_cpu_arch":"x86_64","app_version":"7.5.6","app_build":"0","measure_sdk_version":"0.0.1","device_low_power_mode":false,"app_unique_id":"org.wikimedia.wikipedia"},"user_triggered":false},{"id":"9ab678c2-61dc-466c-a1af-6cdb87a23681","session_id":"84d0b81b-beb4-4eeb-b1ab-3bf2575edd26","timestamp":"2025-01-20T13:58:59.418Z","type":"lifecycle_view_controller","lifecycle_view_controller":{"type":"viewDidDisappear","class_name":"UIPredictionViewController"},"attribute":{"thread_name":"com.apple.main-thread","device_name":"iPhone 15 Pro","device_model":"Simulator iPhone 15 Pro","device_manufacturer":"Apple","device_type":"phone","device_is_foldable":false,"device_is_physical":false,"device_density_dpi":480,"device_width_px":1179,"device_height_px":2556,"device_density":3,"device_locale":"en_IN","os_name":"iOS","os_version":"17.4","platform":"ios","network_type":"wifi","network_generation":"unknown","network_provider":"unknown","installation_id":"6e59eb43-73d3-4829-87d1-d4f1a184725b","user_id":"test_user_id","device_cpu_arch":"x86_64","app_version":"7.5.6","app_build":"0","measure_sdk_version":"0.0.1","device_low_power_mode":false,"app_unique_id":"org.wikimedia.wikipedia"},"user_triggered":false},{"id":"fac2db5f-013c-435f-9e7b-6f3765c51781","session_id":"84d0b81b-beb4-4eeb-b1ab-3bf2575edd26","timestamp":"2025-01-20T13:58:59.432Z","type":"lifecycle_view_controller","lifecycle_view_controller":{"type":"viewDidAppear","class_name":"UIInputWindowController"},"attribute":{"thread_name":"com.apple.main-thread","device_name":"iPhone 15 Pro","device_model":"Simulator iPhone 15 Pro","device_manufacturer":"Apple","device_type":"phone","device_is_foldable":false,"device_is_physical":false,"device_density_dpi":480,"device_width_px":1179,"device_height_px":2556,"device_density":3,"device_locale":"en_IN","os_name":"iOS","os_version":"17.4","platform":"ios","network_type":"wifi","network_generation":"unknown","network_provider":"unknown","installation_id":"6e59eb43-73d3-4829-87d1-d4f1a184725b","user_id":"test_user_id","device_cpu_arch":"x86_64","app_version":"7.5.6","app_build":"0","measure_sdk_version":"0.0.1","device_low_power_mode":false,"app_unique_id":"org.wikimedia.wikipedia"},"user_triggered":false},{"id":"c0e65e7a-e676-4637-953d-1ea6f6c0cea2","session_id":"84d0b81b-beb4-4eeb-b1ab-3bf2575edd26","timestamp":"2025-01-20T13:58:59.442Z","type":"lifecycle_view_controller","lifecycle_view_controller":{"type":"viewDidAppear","class_name":"UICompatibilityInputViewController"},"attribute":{"thread_name":"com.apple.main-thread","device_name":"iPhone 15 Pro","device_model":"Simulator iPhone 15 Pro","device_manufacturer":"Apple","device_type":"phone","device_is_foldable":false,"device_is_physical":false,"device_density_dpi":480,"device_width_px":1179,"device_height_px":2556,"device_density":3,"device_locale":"en_IN","os_name":"iOS","os_version":"17.4","platform":"ios","network_type":"wifi","network_generation":"unknown","network_provider":"unknown","installation_id":"6e59eb43-73d3-4829-87d1-d4f1a184725b","user_id":"test_user_id","device_cpu_arch":"x86_64","app_version":"7.5.6","app_build":"0","measure_sdk_version":"0.0.1","device_low_power_mode":false,"app_unique_id":"org.wikimedia.wikipedia"},"user_triggered":false},{"id":"ae3e8a89-6611-4a61-a227-965254f02329","session_id":"84d0b81b-beb4-4eeb-b1ab-3bf2575edd26","timestamp":"2025-01-20T13:58:59.452Z","type":"lifecycle_view_controller","lifecycle_view_controller":{"type":"viewDidAppear","class_name":"UICompatibilityInputViewController"},"attribute":{"thread_name":"com.apple.main-thread","device_name":"iPhone 15 Pro","device_model":"Simulator iPhone 15 Pro","device_manufacturer":"Apple","device_type":"phone","device_is_foldable":false,"device_is_physical":false,"device_density_dpi":480,"device_width_px":1179,"device_height_px":2556,"device_density":3,"device_locale":"en_IN","os_name":"iOS","os_version":"17.4","platform":"ios","network_type":"wifi","network_generation":"unknown","network_provider":"unknown","installation_id":"6e59eb43-73d3-4829-87d1-d4f1a184725b","user_id":"test_user_id","device_cpu_arch":"x86_64","app_version":"7.5.6","app_build":"0","measure_sdk_version":"0.0.1","device_low_power_mode":false,"app_unique_id":"org.wikimedia.wikipedia"},"user_triggered":false},{"id":"645d5672-98a9-447d-8694-0ca705d5a47c","session_id":"84d0b81b-beb4-4eeb-b1ab-3bf2575edd26","timestamp":"2025-01-20T13:58:59.462Z","type":"lifecycle_view_controller","lifecycle_view_controller":{"type":"viewDidAppear","class_name":"UISystemInputAssistantViewController"},"attribute":{"thread_name":"com.apple.main-thread","device_name":"iPhone 15 Pro","device_model":"Simulator iPhone 15 Pro","device_manufacturer":"Apple","device_type":"phone","device_is_foldable":false,"device_is_physical":false,"device_density_dpi":480,"device_width_px":1179,"device_height_px":2556,"device_density":3,"device_locale":"en_IN","os_name":"iOS","os_version":"17.4","platform":"ios","network_type":"wifi","network_generation":"unknown","network_provider":"unknown","installation_id":"6e59eb43-73d3-4829-87d1-d4f1a184725b","user_id":"test_user_id","device_cpu_arch":"x86_64","app_version":"7.5.6","app_build":"0","measure_sdk_version":"0.0.1","device_low_power_mode":false,"app_unique_id":"org.wikimedia.wikipedia"},"user_triggered":false},{"id":"1f24a239-e615-4c6a-afcb-6b8d3f576531","session_id":"84d0b81b-beb4-4eeb-b1ab-3bf2575edd26","timestamp":"2025-01-20T13:58:59.471Z","type":"lifecycle_view_controller","lifecycle_view_controller":{"type":"viewDidAppear","class_name":"UIPredictionViewController"},"attribute":{"thread_name":"com.apple.main-thread","device_name":"iPhone 15 Pro","device_model":"Simulator iPhone 15 Pro","device_manufacturer":"Apple","device_type":"phone","device_is_foldable":false,"device_is_physical":false,"device_density_dpi":480,"device_width_px":1179,"device_height_px":2556,"device_density":3,"device_locale":"en_IN","os_name":"iOS","os_version":"17.4","platform":"ios","network_type":"wifi","network_generation":"unknown","network_provider":"unknown","installation_id":"6e59eb43-73d3-4829-87d1-d4f1a184725b","user_id":"test_user_id","device_cpu_arch":"x86_64","app_version":"7.5.6","app_build":"0","measure_sdk_version":"0.0.1","device_low_power_mode":false,"app_unique_id":"org.wikimedia.wikipedia"},"user_triggered":false},{"id":"b9b6f88f-f08b-426a-ab9d-8c296162e8a7","session_id":"84d0b81b-beb4-4eeb-b1ab-3bf2575edd26","timestamp":"2025-01-20T13:58:59.479Z","type":"lifecycle_view_controller","lifecycle_view_controller":{"type":"viewDidAppear","class_name":"UISystemKeyboardDockController"},"attribute":{"thread_name":"com.apple.main-thread","device_name":"iPhone 15 Pro","device_model":"Simulator iPhone 15 Pro","device_manufacturer":"Apple","device_type":"phone","device_is_foldable":false,"device_is_physical":false,"device_density_dpi":480,"device_width_px":1179,"device_height_px":2556,"device_density":3,"device_locale":"en_IN","os_name":"iOS","os_version":"17.4","platform":"ios","network_type":"wifi","network_generation":"unknown","network_provider":"unknown","installation_id":"6e59eb43-73d3-4829-87d1-d4f1a184725b","user_id":"test_user_id","device_cpu_arch":"x86_64","app_version":"7.5.6","app_build":"0","measure_sdk_version":"0.0.1","device_low_power_mode":false,"app_unique_id":"org.wikimedia.wikipedia"},"user_triggered":false},{"id":"90cd0d34-20d4-4832-92a6-2c9476d78fab","session_id":"84d0b81b-beb4-4eeb-b1ab-3bf2575edd26","timestamp":"2025-01-20T13:58:59.487Z","type":"lifecycle_view_controller","lifecycle_view_controller":{"type":"viewDidDisappear","class_name":"_UICursorAccessoryViewController"},"attribute":{"thread_name":"com.apple.main-thread","device_name":"iPhone 15 Pro","device_model":"Simulator iPhone 15 Pro","device_manufacturer":"Apple","device_type":"phone","device_is_foldable":false,"device_is_physical":false,"device_density_dpi":480,"device_width_px":1179,"device_height_px":2556,"device_density":3,"device_locale":"en_IN","os_name":"iOS","os_version":"17.4","platform":"ios","network_type":"wifi","network_generation":"unknown","network_provider":"unknown","installation_id":"6e59eb43-73d3-4829-87d1-d4f1a184725b","user_id":"test_user_id","device_cpu_arch":"x86_64","app_version":"7.5.6","app_build":"0","measure_sdk_version":"0.0.1","device_low_power_mode":false,"app_unique_id":"org.wikimedia.wikipedia"},"user_triggered":false},{"id":"255a6413-9ee7-48ba-a5a6-bfe50542cf98","session_id":"84d0b81b-beb4-4eeb-b1ab-3bf2575edd26","timestamp":"2025-01-20T13:58:59.494Z","type":"lifecycle_view_controller","lifecycle_view_controller":{"type":"viewDidDisappear","class_name":"RootNavigationController"},"attribute":{"thread_name":"com.apple.main-thread","device_name":"iPhone 15 Pro","device_model":"Simulator iPhone 15 Pro","device_manufacturer":"Apple","device_type":"phone","device_is_foldable":false,"device_is_physical":false,"device_density_dpi":480,"device_width_px":1179,"device_height_px":2556,"device_density":3,"device_locale":"en_IN","os_name":"iOS","os_version":"17.4","platform":"ios","network_type":"wifi","network_generation":"unknown","network_provider":"unknown","installation_id":"6e59eb43-73d3-4829-87d1-d4f1a184725b","user_id":"test_user_id","device_cpu_arch":"x86_64","app_version":"7.5.6","app_build":"0","measure_sdk_version":"0.0.1","device_low_power_mode":false,"app_unique_id":"org.wikimedia.wikipedia"},"user_triggered":false},{"id":"eb024439-46bc-48f4-924c-fe22036f9424","session_id":"84d0b81b-beb4-4eeb-b1ab-3bf2575edd26","timestamp":"2025-01-20T13:58:59.502Z","type":"lifecycle_view_controller","lifecycle_view_controller":{"type":"viewDidDisappear","class_name":"SearchViewController"},"attribute":{"thread_name":"com.apple.main-thread","device_name":"iPhone 15 Pro","device_model":"Simulator iPhone 15 Pro","device_manufacturer":"Apple","device_type":"phone","device_is_foldable":false,"device_is_physical":false,"device_density_dpi":480,"device_width_px":1179,"device_height_px":2556,"device_density":3,"device_locale":"en_IN","os_name":"iOS","os_version":"17.4","platform":"ios","network_type":"wifi","network_generation":"unknown","network_provider":"unknown","installation_id":"6e59eb43-73d3-4829-87d1-d4f1a184725b","user_id":"test_user_id","device_cpu_arch":"x86_64","app_version":"7.5.6","app_build":"0","measure_sdk_version":"0.0.1","device_low_power_mode":false,"app_unique_id":"org.wikimedia.wikipedia"},"user_triggered":false},{"id":"3851c5d2-fdd4-40d1-bedf-fb39f680c0b5","session_id":"84d0b81b-beb4-4eeb-b1ab-3bf2575edd26","timestamp":"2025-01-20T13:58:59.511Z","type":"lifecycle_view_controller","lifecycle_view_controller":{"type":"viewDidDisappear","class_name":"SearchResultsViewController"},"attribute":{"thread_name":"com.apple.main-thread","device_name":"iPhone 15 Pro","device_model":"Simulator iPhone 15 Pro","device_manufacturer":"Apple","device_type":"phone","device_is_foldable":false,"device_is_physical":false,"device_density_dpi":480,"device_width_px":1179,"device_height_px":2556,"device_density":3,"device_locale":"en_IN","os_name":"iOS","os_version":"17.4","platform":"ios","network_type":"wifi","network_generation":"unknown","network_provider":"unknown","installation_id":"6e59eb43-73d3-4829-87d1-d4f1a184725b","user_id":"test_user_id","device_cpu_arch":"x86_64","app_version":"7.5.6","app_build":"0","measure_sdk_version":"0.0.1","device_low_power_mode":false,"app_unique_id":"org.wikimedia.wikipedia"},"user_triggered":false},{"id":"5b91f569-3bcd-4f78-b8a6-b524672cdcd8","session_id":"84d0b81b-beb4-4eeb-b1ab-3bf2575edd26","timestamp":"2025-01-20T13:58:59.519Z","type":"lifecycle_view_controller","lifecycle_view_controller":{"type":"viewDidDisappear","class_name":"SearchLanguagesBarViewController"},"attribute":{"thread_name":"com.apple.main-thread","device_name":"iPhone 15 Pro","device_model":"Simulator iPhone 15 Pro","device_manufacturer":"Apple","device_type":"phone","device_is_foldable":false,"device_is_physical":false,"device_density_dpi":480,"device_width_px":1179,"device_height_px":2556,"device_density":3,"device_locale":"en_IN","os_name":"iOS","os_version":"17.4","platform":"ios","network_type":"wifi","network_generation":"unknown","network_provider":"unknown","installation_id":"6e59eb43-73d3-4829-87d1-d4f1a184725b","user_id":"test_user_id","device_cpu_arch":"x86_64","app_version":"7.5.6","app_build":"0","measure_sdk_version":"0.0.1","device_low_power_mode":false,"app_unique_id":"org.wikimedia.wikipedia"},"user_triggered":false},{"id":"5faa4a8a-fe7b-45e1-ad35-ce551b674f62","session_id":"84d0b81b-beb4-4eeb-b1ab-3bf2575edd26","timestamp":"2025-01-20T13:58:59.531Z","type":"lifecycle_view_controller","lifecycle_view_controller":{"type":"viewDidAppear","class_name":"RootNavigationController"},"attribute":{"thread_name":"com.apple.main-thread","device_name":"iPhone 15 Pro","device_model":"Simulator iPhone 15 Pro","device_manufacturer":"Apple","device_type":"phone","device_is_foldable":false,"device_is_physical":false,"device_density_dpi":480,"device_width_px":1179,"device_height_px":2556,"device_density":3,"device_locale":"en_IN","os_name":"iOS","os_version":"17.4","platform":"ios","network_type":"wifi","network_generation":"unknown","network_provider":"unknown","installation_id":"6e59eb43-73d3-4829-87d1-d4f1a184725b","user_id":"test_user_id","device_cpu_arch":"x86_64","app_version":"7.5.6","app_build":"0","measure_sdk_version":"0.0.1","device_low_power_mode":false,"app_unique_id":"org.wikimedia.wikipedia"},"user_triggered":false},{"id":"e82e4625-42ac-4023-a0a6-b88cde074016","session_id":"84d0b81b-beb4-4eeb-b1ab-3bf2575edd26","timestamp":"2025-01-20T13:58:59.542Z","type":"lifecycle_view_controller","lifecycle_view_controller":{"type":"viewDidAppear","class_name":"ExploreViewController"},"attribute":{"thread_name":"com.apple.main-thread","device_name":"iPhone 15 Pro","device_model":"Simulator iPhone 15 Pro","device_manufacturer":"Apple","device_type":"phone","device_is_foldable":false,"device_is_physical":false,"device_density_dpi":480,"device_width_px":1179,"device_height_px":2556,"device_density":3,"device_locale":"en_IN","os_name":"iOS","os_version":"17.4","platform":"ios","network_type":"wifi","network_generation":"unknown","network_provider":"unknown","installation_id":"6e59eb43-73d3-4829-87d1-d4f1a184725b","user_id":"test_user_id","device_cpu_arch":"x86_64","app_version":"7.5.6","app_build":"0","measure_sdk_version":"0.0.1","device_low_power_mode":false,"app_unique_id":"org.wikimedia.wikipedia"},"user_triggered":false},{"id":"6797f848-ee54-4aea-af89-ab471264441e","session_id":"84d0b81b-beb4-4eeb-b1ab-3bf2575edd26","timestamp":"2025-01-20T13:58:59.553Z","type":"lifecycle_view_controller","lifecycle_view_controller":{"type":"viewDidAppear","class_name":"ExploreCardViewController"},"attribute":{"thread_name":"com.apple.main-thread","device_name":"iPhone 15 Pro","device_model":"Simulator iPhone 15 Pro","device_manufacturer":"Apple","device_type":"phone","device_is_foldable":false,"device_is_physical":false,"device_density_dpi":480,"device_width_px":1179,"device_height_px":2556,"device_density":3,"device_locale":"en_IN","os_name":"iOS","os_version":"17.4","platform":"ios","network_type":"wifi","network_generation":"unknown","network_provider":"unknown","installation_id":"6e59eb43-73d3-4829-87d1-d4f1a184725b","user_id":"test_user_id","device_cpu_arch":"x86_64","app_version":"7.5.6","app_build":"0","measure_sdk_version":"0.0.1","device_low_power_mode":false,"app_unique_id":"org.wikimedia.wikipedia"},"user_triggered":false},{"id":"f26c7a33-25c1-4be5-96b0-de4ffcc2b16b","session_id":"84d0b81b-beb4-4eeb-b1ab-3bf2575edd26","timestamp":"2025-01-20T13:58:59.566Z","type":"lifecycle_view_controller","lifecycle_view_controller":{"type":"viewDidAppear","class_name":"ExploreCardViewController"},"attribute":{"thread_name":"com.apple.main-thread","device_name":"iPhone 15 Pro","device_model":"Simulator iPhone 15 Pro","device_manufacturer":"Apple","device_type":"phone","device_is_foldable":false,"device_is_physical":false,"device_density_dpi":480,"device_width_px":1179,"device_height_px":2556,"device_density":3,"device_locale":"en_IN","os_name":"iOS","os_version":"17.4","platform":"ios","network_type":"wifi","network_generation":"unknown","network_provider":"unknown","installation_id":"6e59eb43-73d3-4829-87d1-d4f1a184725b","user_id":"test_user_id","device_cpu_arch":"x86_64","app_version":"7.5.6","app_build":"0","measure_sdk_version":"0.0.1","device_low_power_mode":false,"app_unique_id":"org.wikimedia.wikipedia"},"user_triggered":false},{"id":"25eb6dfc-b3b9-4709-8d93-4d914f3802d9","session_id":"84d0b81b-beb4-4eeb-b1ab-3bf2575edd26","timestamp":"2025-01-20T13:58:59.579Z","type":"lifecycle_view_controller","lifecycle_view_controller":{"type":"viewDidAppear","class_name":"ExploreCardViewController"},"attribute":{"thread_name":"com.apple.main-thread","device_name":"iPhone 15 Pro","device_model":"Simulator iPhone 15 Pro","device_manufacturer":"Apple","device_type":"phone","device_is_foldable":false,"device_is_physical":false,"device_density_dpi":480,"device_width_px":1179,"device_height_px":2556,"device_density":3,"device_locale":"en_IN","os_name":"iOS","os_version":"17.4","platform":"ios","network_type":"wifi","network_generation":"unknown","network_provider":"unknown","installation_id":"6e59eb43-73d3-4829-87d1-d4f1a184725b","user_id":"test_user_id","device_cpu_arch":"x86_64","app_version":"7.5.6","app_build":"0","measure_sdk_version":"0.0.1","device_low_power_mode":false,"app_unique_id":"org.wikimedia.wikipedia"},"user_triggered":false},{"id":"d452413b-2ff5-4c30-a3dd-5ba250d10c5f","session_id":"84d0b81b-beb4-4eeb-b1ab-3bf2575edd26","timestamp":"2025-01-20T13:58:59.592Z","type":"lifecycle_view_controller","lifecycle_view_controller":{"type":"viewDidAppear","class_name":"ExploreCardViewController"},"attribute":{"thread_name":"com.apple.main-thread","device_name":"iPhone 15 Pro","device_model":"Simulator iPhone 15 Pro","device_manufacturer":"Apple","device_type":"phone","device_is_foldable":false,"device_is_physical":false,"device_density_dpi":480,"device_width_px":1179,"device_height_px":2556,"device_density":3,"device_locale":"en_IN","os_name":"iOS","os_version":"17.4","platform":"ios","network_type":"wifi","network_generation":"unknown","network_provider":"unknown","installation_id":"6e59eb43-73d3-4829-87d1-d4f1a184725b","user_id":"test_user_id","device_cpu_arch":"x86_64","app_version":"7.5.6","app_build":"0","measure_sdk_version":"0.0.1","device_low_power_mode":false,"app_unique_id":"org.wikimedia.wikipedia"},"user_triggered":false},{"id":"7dbe3fb0-fe2a-4c36-9517-67e5f098cab6","session_id":"84d0b81b-beb4-4eeb-b1ab-3bf2575edd26","timestamp":"2025-01-20T13:58:59.610Z","type":"lifecycle_view_controller","lifecycle_view_controller":{"type":"viewDidAppear","class_name":"ExploreCardViewController"},"attribute":{"thread_name":"com.apple.main-thread","device_name":"iPhone 15 Pro","device_model":"Simulator iPhone 15 Pro","device_manufacturer":"Apple","device_type":"phone","device_is_foldable":false,"device_is_physical":false,"device_density_dpi":480,"device_width_px":1179,"device_height_px":2556,"device_density":3,"device_locale":"en_IN","os_name":"iOS","os_version":"17.4","platform":"ios","network_type":"wifi","network_generation":"unknown","network_provider":"unknown","installation_id":"6e59eb43-73d3-4829-87d1-d4f1a184725b","user_id":"test_user_id","device_cpu_arch":"x86_64","app_version":"7.5.6","app_build":"0","measure_sdk_version":"0.0.1","device_low_power_mode":false,"app_unique_id":"org.wikimedia.wikipedia"},"user_triggered":false},{"id":"1d9f8e21-68d8-4a86-a838-5aa39872e046","session_id":"84d0b81b-beb4-4eeb-b1ab-3bf2575edd26","timestamp":"2025-01-20T13:58:59.626Z","type":"lifecycle_view_controller","lifecycle_view_controller":{"type":"viewDidDisappear","class_name":"UICompatibilityInputViewController"},"attribute":{"thread_name":"com.apple.main-thread","device_name":"iPhone 15 Pro","device_model":"Simulator iPhone 15 Pro","device_manufacturer":"Apple","device_type":"phone","device_is_foldable":false,"device_is_physical":false,"device_density_dpi":480,"device_width_px":1179,"device_height_px":2556,"device_density":3,"device_locale":"en_IN","os_name":"iOS","os_version":"17.4","platform":"ios","network_type":"wifi","network_generation":"unknown","network_provider":"unknown","installation_id":"6e59eb43-73d3-4829-87d1-d4f1a184725b","user_id":"test_user_id","device_cpu_arch":"x86_64","app_version":"7.5.6","app_build":"0","measure_sdk_version":"0.0.1","device_low_power_mode":false,"app_unique_id":"org.wikimedia.wikipedia"},"user_triggered":false},{"id":"91924f6f-ee7b-43f0-ad3a-a15f406497e9","session_id":"84d0b81b-beb4-4eeb-b1ab-3bf2575edd26","timestamp":"2025-01-20T13:59:01.323Z","type":"memory_usage_absolute","memory_usage_absolute":{"interval":2000,"used_memory":131904,"max_memory":16777216},"attribute":{"thread_name":"com.apple.main-thread","device_name":"iPhone 15 Pro","device_model":"Simulator iPhone 15 Pro","device_manufacturer":"Apple","device_type":"phone","device_is_foldable":false,"device_is_physical":false,"device_density_dpi":480,"device_width_px":1179,"device_height_px":2556,"device_density":3,"device_locale":"en_IN","os_name":"iOS","os_version":"17.4","platform":"ios","network_type":"wifi","network_generation":"unknown","network_provider":"unknown","installation_id":"6e59eb43-73d3-4829-87d1-d4f1a184725b","user_id":"test_user_id","device_cpu_arch":"x86_64","app_version":"7.5.6","app_build":"0","measure_sdk_version":"0.0.1","device_low_power_mode":false,"app_unique_id":"org.wikimedia.wikipedia"},"user_triggered":false},{"id":"9b8a96a0-7da3-4a19-b83a-18ff25f01d6b","session_id":"84d0b81b-beb4-4eeb-b1ab-3bf2575edd26","timestamp":"2025-01-20T13:59:02.060Z","type":"cpu_usage","cpu_usage":{"num_cores":12,"clock_speed":2600000000,"start_time":0,"uptime":0,"utime":0,"cutime":0,"cstime":0,"stime":0,"interval":3000,"percentage_usage":4.2},"attribute":{"thread_name":"com.apple.main-thread","device_name":"iPhone 15 Pro","device_model":"Simulator iPhone 15 Pro","device_manufacturer":"Apple","device_type":"phone","device_is_foldable":false,"device_is_physical":false,"device_density_dpi":480,"device_width_px":1179,"device_height_px":2556,"device_density":3,"device_locale":"en_IN","os_name":"iOS","os_version":"17.4","platform":"ios","network_type":"wifi","network_generation":"unknown","network_provider":"unknown","installation_id":"6e59eb43-73d3-4829-87d1-d4f1a184725b","user_id":"test_user_id","device_cpu_arch":"x86_64","app_version":"7.5.6","app_build":"0","measure_sdk_version":"0.0.1","device_low_power_mode":false,"app_unique_id":"org.wikimedia.wikipedia"},"user_triggered":false},{"id":"1eee7746-203d-475c-aa9a-6c159476a1ca","session_id":"84d0b81b-beb4-4eeb-b1ab-3bf2575edd26","timestamp":"2025-01-20T13:59:02.421Z","type":"lifecycle_view_controller","lifecycle_view_controller":{"type":"viewDidLoad","class_name":"ArticleViewController"},"attribute":{"thread_name":"com.apple.main-thread","device_name":"iPhone 15 Pro","device_model":"Simulator iPhone 15 Pro","device_manufacturer":"Apple","device_type":"phone","device_is_foldable":false,"device_is_physical":false,"device_density_dpi":480,"device_width_px":1179,"device_height_px":2556,"device_density":3,"device_locale":"en_IN","os_name":"iOS","os_version":"17.4","platform":"ios","network_type":"wifi","network_generation":"unknown","network_provider":"unknown","installation_id":"6e59eb43-73d3-4829-87d1-d4f1a184725b","user_id":"test_user_id","device_cpu_arch":"x86_64","app_version":"7.5.6","app_build":"0","measure_sdk_version":"0.0.1","device_low_power_mode":false,"app_unique_id":"org.wikimedia.wikipedia"},"user_triggered":false},{"id":"9b97ccaa-54a1-4517-b598-90b8da30b614","session_id":"84d0b81b-beb4-4eeb-b1ab-3bf2575edd26","timestamp":"2025-01-20T13:59:02.453Z","type":"lifecycle_view_controller","lifecycle_view_controller":{"type":"viewWillDisappear","class_name":"ExploreViewController"},"attribute":{"thread_name":"com.apple.main-thread","device_name":"iPhone 15 Pro","device_model":"Simulator iPhone 15 Pro","device_manufacturer":"Apple","device_type":"phone","device_is_foldable":false,"device_is_physical":false,"device_density_dpi":480,"device_width_px":1179,"device_height_px":2556,"device_density":3,"device_locale":"en_IN","os_name":"iOS","os_version":"17.4","platform":"ios","network_type":"wifi","network_generation":"unknown","network_provider":"unknown","installation_id":"6e59eb43-73d3-4829-87d1-d4f1a184725b","user_id":"test_user_id","device_cpu_arch":"x86_64","app_version":"7.5.6","app_build":"0","measure_sdk_version":"0.0.1","device_low_power_mode":false,"app_unique_id":"org.wikimedia.wikipedia"},"user_triggered":false},{"id":"8def4d03-a32e-4a93-9638-9487a06f9167","session_id":"84d0b81b-beb4-4eeb-b1ab-3bf2575edd26","timestamp":"2025-01-20T13:59:02.461Z","type":"lifecycle_view_controller","lifecycle_view_controller":{"type":"viewWillDisappear","class_name":"ExploreCardViewController"},"attribute":{"thread_name":"com.apple.main-thread","device_name":"iPhone 15 Pro","device_model":"Simulator iPhone 15 Pro","device_manufacturer":"Apple","device_type":"phone","device_is_foldable":false,"device_is_physical":false,"device_density_dpi":480,"device_width_px":1179,"device_height_px":2556,"device_density":3,"device_locale":"en_IN","os_name":"iOS","os_version":"17.4","platform":"ios","network_type":"wifi","network_generation":"unknown","network_provider":"unknown","installation_id":"6e59eb43-73d3-4829-87d1-d4f1a184725b","user_id":"test_user_id","device_cpu_arch":"x86_64","app_version":"7.5.6","app_build":"0","measure_sdk_version":"0.0.1","device_low_power_mode":false,"app_unique_id":"org.wikimedia.wikipedia"},"user_triggered":false},{"id":"44cf27ab-ead3-4c6f-8bf8-a4bf9044b10d","session_id":"84d0b81b-beb4-4eeb-b1ab-3bf2575edd26","timestamp":"2025-01-20T13:59:02.470Z","type":"lifecycle_view_controller","lifecycle_view_controller":{"type":"viewWillDisappear","class_name":"ExploreCardViewController"},"attribute":{"thread_name":"com.apple.main-thread","device_name":"iPhone 15 Pro","device_model":"Simulator iPhone 15 Pro","device_manufacturer":"Apple","device_type":"phone","device_is_foldable":false,"device_is_physical":false,"device_density_dpi":480,"device_width_px":1179,"device_height_px":2556,"device_density":3,"device_locale":"en_IN","os_name":"iOS","os_version":"17.4","platform":"ios","network_type":"wifi","network_generation":"unknown","network_provider":"unknown","installation_id":"6e59eb43-73d3-4829-87d1-d4f1a184725b","user_id":"test_user_id","device_cpu_arch":"x86_64","app_version":"7.5.6","app_build":"0","measure_sdk_version":"0.0.1","device_low_power_mode":false,"app_unique_id":"org.wikimedia.wikipedia"},"user_triggered":false},{"id":"a058f28e-2ace-4836-b155-4fce502b74a1","session_id":"84d0b81b-beb4-4eeb-b1ab-3bf2575edd26","timestamp":"2025-01-20T13:59:02.480Z","type":"lifecycle_view_controller","lifecycle_view_controller":{"type":"viewWillDisappear","class_name":"ExploreCardViewController"},"attribute":{"thread_name":"com.apple.main-thread","device_name":"iPhone 15 Pro","device_model":"Simulator iPhone 15 Pro","device_manufacturer":"Apple","device_type":"phone","device_is_foldable":false,"device_is_physical":false,"device_density_dpi":480,"device_width_px":1179,"device_height_px":2556,"device_density":3,"device_locale":"en_IN","os_name":"iOS","os_version":"17.4","platform":"ios","network_type":"wifi","network_generation":"unknown","network_provider":"unknown","installation_id":"6e59eb43-73d3-4829-87d1-d4f1a184725b","user_id":"test_user_id","device_cpu_arch":"x86_64","app_version":"7.5.6","app_build":"0","measure_sdk_version":"0.0.1","device_low_power_mode":false,"app_unique_id":"org.wikimedia.wikipedia"},"user_triggered":false},{"id":"31d3b9da-9b3b-443c-b394-42f6ca5a8ce9","session_id":"84d0b81b-beb4-4eeb-b1ab-3bf2575edd26","timestamp":"2025-01-20T13:59:02.490Z","type":"lifecycle_view_controller","lifecycle_view_controller":{"type":"viewWillDisappear","class_name":"ExploreCardViewController"},"attribute":{"thread_name":"com.apple.main-thread","device_name":"iPhone 15 Pro","device_model":"Simulator iPhone 15 Pro","device_manufacturer":"Apple","device_type":"phone","device_is_foldable":false,"device_is_physical":false,"device_density_dpi":480,"device_width_px":1179,"device_height_px":2556,"device_density":3,"device_locale":"en_IN","os_name":"iOS","os_version":"17.4","platform":"ios","network_type":"wifi","network_generation":"unknown","network_provider":"unknown","installation_id":"6e59eb43-73d3-4829-87d1-d4f1a184725b","user_id":"test_user_id","device_cpu_arch":"x86_64","app_version":"7.5.6","app_build":"0","measure_sdk_version":"0.0.1","device_low_power_mode":false,"app_unique_id":"org.wikimedia.wikipedia"},"user_triggered":false},{"id":"04231a7e-1ba2-4a55-97ed-3a74abc4c94c","session_id":"84d0b81b-beb4-4eeb-b1ab-3bf2575edd26","timestamp":"2025-01-20T13:59:02.500Z","type":"lifecycle_view_controller","lifecycle_view_controller":{"type":"viewWillDisappear","class_name":"ExploreCardViewController"},"attribute":{"thread_name":"com.apple.main-thread","device_name":"iPhone 15 Pro","device_model":"Simulator iPhone 15 Pro","device_manufacturer":"Apple","device_type":"phone","device_is_foldable":false,"device_is_physical":false,"device_density_dpi":480,"device_width_px":1179,"device_height_px":2556,"device_density":3,"device_locale":"en_IN","os_name":"iOS","os_version":"17.4","platform":"ios","network_type":"wifi","network_generation":"unknown","network_provider":"unknown","installation_id":"6e59eb43-73d3-4829-87d1-d4f1a184725b","user_id":"test_user_id","device_cpu_arch":"x86_64","app_version":"7.5.6","app_build":"0","measure_sdk_version":"0.0.1","device_low_power_mode":false,"app_unique_id":"org.wikimedia.wikipedia"},"user_triggered":false},{"id":"0d9e2418-69c6-45bd-86ea-983f05859bc4","session_id":"84d0b81b-beb4-4eeb-b1ab-3bf2575edd26","timestamp":"2025-01-20T13:59:02.509Z","type":"lifecycle_view_controller","lifecycle_view_controller":{"type":"viewWillAppear","class_name":"ArticleViewController"},"attribute":{"thread_name":"com.apple.main-thread","device_name":"iPhone 15 Pro","device_model":"Simulator iPhone 15 Pro","device_manufacturer":"Apple","device_type":"phone","device_is_foldable":false,"device_is_physical":false,"device_density_dpi":480,"device_width_px":1179,"device_height_px":2556,"device_density":3,"device_locale":"en_IN","os_name":"iOS","os_version":"17.4","platform":"ios","network_type":"wifi","network_generation":"unknown","network_provider":"unknown","installation_id":"6e59eb43-73d3-4829-87d1-d4f1a184725b","user_id":"test_user_id","device_cpu_arch":"x86_64","app_version":"7.5.6","app_build":"0","measure_sdk_version":"0.0.1","device_low_power_mode":false,"app_unique_id":"org.wikimedia.wikipedia"},"user_triggered":false},{"id":"3a65a11b-835b-4860-a6ec-99733fa9f2ca","session_id":"84d0b81b-beb4-4eeb-b1ab-3bf2575edd26","timestamp":"2025-01-20T13:59:02.972Z","type":"lifecycle_view_controller","lifecycle_view_controller":{"type":"viewDidDisappear","class_name":"ExploreViewController"},"attribute":{"thread_name":"com.apple.main-thread","device_name":"iPhone 15 Pro","device_model":"Simulator iPhone 15 Pro","device_manufacturer":"Apple","device_type":"phone","device_is_foldable":false,"device_is_physical":false,"device_density_dpi":480,"device_width_px":1179,"device_height_px":2556,"device_density":3,"device_locale":"en_IN","os_name":"iOS","os_version":"17.4","platform":"ios","network_type":"wifi","network_generation":"unknown","network_provider":"unknown","installation_id":"6e59eb43-73d3-4829-87d1-d4f1a184725b","user_id":"test_user_id","device_cpu_arch":"x86_64","app_version":"7.5.6","app_build":"0","measure_sdk_version":"0.0.1","device_low_power_mode":false,"app_unique_id":"org.wikimedia.wikipedia"},"user_triggered":false},{"id":"99ffb37d-ceb3-45b8-bc45-3ddd2411dae3","session_id":"84d0b81b-beb4-4eeb-b1ab-3bf2575edd26","timestamp":"2025-01-20T13:59:02.989Z","type":"lifecycle_view_controller","lifecycle_view_controller":{"type":"viewDidDisappear","class_name":"ExploreCardViewController"},"attribute":{"thread_name":"com.apple.main-thread","device_name":"iPhone 15 Pro","device_model":"Simulator iPhone 15 Pro","device_manufacturer":"Apple","device_type":"phone","device_is_foldable":false,"device_is_physical":false,"device_density_dpi":480,"device_width_px":1179,"device_height_px":2556,"device_density":3,"device_locale":"en_IN","os_name":"iOS","os_version":"17.4","platform":"ios","network_type":"wifi","network_generation":"unknown","network_provider":"unknown","installation_id":"6e59eb43-73d3-4829-87d1-d4f1a184725b","user_id":"test_user_id","device_cpu_arch":"x86_64","app_version":"7.5.6","app_build":"0","measure_sdk_version":"0.0.1","device_low_power_mode":false,"app_unique_id":"org.wikimedia.wikipedia"},"user_triggered":false},{"id":"4dab9997-56a8-4d60-bffc-e01a3cb31e4e","session_id":"84d0b81b-beb4-4eeb-b1ab-3bf2575edd26","timestamp":"2025-01-20T13:59:03.007Z","type":"lifecycle_view_controller","lifecycle_view_controller":{"type":"viewDidDisappear","class_name":"ExploreCardViewController"},"attribute":{"thread_name":"com.apple.main-thread","device_name":"iPhone 15 Pro","device_model":"Simulator iPhone 15 Pro","device_manufacturer":"Apple","device_type":"phone","device_is_foldable":false,"device_is_physical":false,"device_density_dpi":480,"device_width_px":1179,"device_height_px":2556,"device_density":3,"device_locale":"en_IN","os_name":"iOS","os_version":"17.4","platform":"ios","network_type":"wifi","network_generation":"unknown","network_provider":"unknown","installation_id":"6e59eb43-73d3-4829-87d1-d4f1a184725b","user_id":"test_user_id","device_cpu_arch":"x86_64","app_version":"7.5.6","app_build":"0","measure_sdk_version":"0.0.1","device_low_power_mode":false,"app_unique_id":"org.wikimedia.wikipedia"},"user_triggered":false},{"id":"8eb6d91c-328c-4849-b616-46d5e95380c7","session_id":"84d0b81b-beb4-4eeb-b1ab-3bf2575edd26","timestamp":"2025-01-20T13:59:03.023Z","type":"lifecycle_view_controller","lifecycle_view_controller":{"type":"viewDidDisappear","class_name":"ExploreCardViewController"},"attribute":{"thread_name":"com.apple.main-thread","device_name":"iPhone 15 Pro","device_model":"Simulator iPhone 15 Pro","device_manufacturer":"Apple","device_type":"phone","device_is_foldable":false,"device_is_physical":false,"device_density_dpi":480,"device_width_px":1179,"device_height_px":2556,"device_density":3,"device_locale":"en_IN","os_name":"iOS","os_version":"17.4","platform":"ios","network_type":"wifi","network_generation":"unknown","network_provider":"unknown","installation_id":"6e59eb43-73d3-4829-87d1-d4f1a184725b","user_id":"test_user_id","device_cpu_arch":"x86_64","app_version":"7.5.6","app_build":"0","measure_sdk_version":"0.0.1","device_low_power_mode":false,"app_unique_id":"org.wikimedia.wikipedia"},"user_triggered":false},{"id":"bbf12811-97b1-4d53-b3a2-1ac70d767381","session_id":"84d0b81b-beb4-4eeb-b1ab-3bf2575edd26","timestamp":"2025-01-20T13:59:03.042Z","type":"lifecycle_view_controller","lifecycle_view_controller":{"type":"viewDidDisappear","class_name":"ExploreCardViewController"},"attribute":{"thread_name":"com.apple.main-thread","device_name":"iPhone 15 Pro","device_model":"Simulator iPhone 15 Pro","device_manufacturer":"Apple","device_type":"phone","device_is_foldable":false,"device_is_physical":false,"device_density_dpi":480,"device_width_px":1179,"device_height_px":2556,"device_density":3,"device_locale":"en_IN","os_name":"iOS","os_version":"17.4","platform":"ios","network_type":"wifi","network_generation":"unknown","network_provider":"unknown","installation_id":"6e59eb43-73d3-4829-87d1-d4f1a184725b","user_id":"test_user_id","device_cpu_arch":"x86_64","app_version":"7.5.6","app_build":"0","measure_sdk_version":"0.0.1","device_low_power_mode":false,"app_unique_id":"org.wikimedia.wikipedia"},"user_triggered":false},{"id":"337b250f-f652-459e-b2d0-1262705805cf","session_id":"84d0b81b-beb4-4eeb-b1ab-3bf2575edd26","timestamp":"2025-01-20T13:59:03.058Z","type":"lifecycle_view_controller","lifecycle_view_controller":{"type":"viewDidDisappear","class_name":"ExploreCardViewController"},"attribute":{"thread_name":"com.apple.main-thread","device_name":"iPhone 15 Pro","device_model":"Simulator iPhone 15 Pro","device_manufacturer":"Apple","device_type":"phone","device_is_foldable":false,"device_is_physical":false,"device_density_dpi":480,"device_width_px":1179,"device_height_px":2556,"device_density":3,"device_locale":"en_IN","os_name":"iOS","os_version":"17.4","platform":"ios","network_type":"wifi","network_generation":"unknown","network_provider":"unknown","installation_id":"6e59eb43-73d3-4829-87d1-d4f1a184725b","user_id":"test_user_id","device_cpu_arch":"x86_64","app_version":"7.5.6","app_build":"0","measure_sdk_version":"0.0.1","device_low_power_mode":false,"app_unique_id":"org.wikimedia.wikipedia"},"user_triggered":false},{"id":"23f4c4c8-c720-49aa-91ad-188fa2e43708","session_id":"84d0b81b-beb4-4eeb-b1ab-3bf2575edd26","timestamp":"2025-01-20T13:59:03.074Z","type":"lifecycle_view_controller","lifecycle_view_controller":{"type":"viewDidAppear","class_name":"ArticleViewController"},"attribute":{"thread_name":"com.apple.main-thread","device_name":"iPhone 15 Pro","device_model":"Simulator iPhone 15 Pro","device_manufacturer":"Apple","device_type":"phone","device_is_foldable":false,"device_is_physical":false,"device_density_dpi":480,"device_width_px":1179,"device_height_px":2556,"device_density":3,"device_locale":"en_IN","os_name":"iOS","os_version":"17.4","platform":"ios","network_type":"wifi","network_generation":"unknown","network_provider":"unknown","installation_id":"6e59eb43-73d3-4829-87d1-d4f1a184725b","user_id":"test_user_id","device_cpu_arch":"x86_64","app_version":"7.5.6","app_build":"0","measure_sdk_version":"0.0.1","device_low_power_mode":false,"app_unique_id":"org.wikimedia.wikipedia"},"user_triggered":false},{"id":"5f1644cd-8e0a-4a2a-80f8-dd1d256a883d","session_id":"84d0b81b-beb4-4eeb-b1ab-3bf2575edd26","timestamp":"2025-01-20T13:59:03.104Z","type":"memory_usage_absolute","memory_usage_absolute":{"interval":2000,"used_memory":134444,"max_memory":16777216},"attribute":{"thread_name":"com.apple.main-thread","device_name":"iPhone 15 Pro","device_model":"Simulator iPhone 15 Pro","device_manufacturer":"Apple","device_type":"phone","device_is_foldable":false,"device_is_physical":false,"device_density_dpi":480,"device_width_px":1179,"device_height_px":2556,"device_density":3,"device_locale":"en_IN","os_name":"iOS","os_version":"17.4","platform":"ios","network_type":"wifi","network_generation":"unknown","network_provider":"unknown","installation_id":"6e59eb43-73d3-4829-87d1-d4f1a184725b","user_id":"test_user_id","device_cpu_arch":"x86_64","app_version":"7.5.6","app_build":"0","measure_sdk_version":"0.0.1","device_low_power_mode":false,"app_unique_id":"org.wikimedia.wikipedia"},"user_triggered":false},{"id":"abfee424-b307-4204-9c8b-2d8eb016c392","session_id":"84d0b81b-beb4-4eeb-b1ab-3bf2575edd26","timestamp":"2025-01-20T13:59:04.825Z","type":"lifecycle_view_controller","lifecycle_view_controller":{"type":"viewWillDisappear","class_name":"ArticleViewController"},"attribute":{"thread_name":"com.apple.main-thread","device_name":"iPhone 15 Pro","device_model":"Simulator iPhone 15 Pro","device_manufacturer":"Apple","device_type":"phone","device_is_foldable":false,"device_is_physical":false,"device_density_dpi":480,"device_width_px":1179,"device_height_px":2556,"device_density":3,"device_locale":"en_IN","os_name":"iOS","os_version":"17.4","platform":"ios","network_type":"wifi","network_generation":"unknown","network_provider":"unknown","installation_id":"6e59eb43-73d3-4829-87d1-d4f1a184725b","user_id":"test_user_id","device_cpu_arch":"x86_64","app_version":"7.5.6","app_build":"0","measure_sdk_version":"0.0.1","device_low_power_mode":false,"app_unique_id":"org.wikimedia.wikipedia"},"user_triggered":false},{"id":"b492a0ac-8689-462f-8676-e331cbe56c10","session_id":"84d0b81b-beb4-4eeb-b1ab-3bf2575edd26","timestamp":"2025-01-20T13:59:04.835Z","type":"lifecycle_view_controller","lifecycle_view_controller":{"type":"viewWillAppear","class_name":"ExploreViewController"},"attribute":{"thread_name":"com.apple.main-thread","device_name":"iPhone 15 Pro","device_model":"Simulator iPhone 15 Pro","device_manufacturer":"Apple","device_type":"phone","device_is_foldable":false,"device_is_physical":false,"device_density_dpi":480,"device_width_px":1179,"device_height_px":2556,"device_density":3,"device_locale":"en_IN","os_name":"iOS","os_version":"17.4","platform":"ios","network_type":"wifi","network_generation":"unknown","network_provider":"unknown","installation_id":"6e59eb43-73d3-4829-87d1-d4f1a184725b","user_id":"test_user_id","device_cpu_arch":"x86_64","app_version":"7.5.6","app_build":"0","measure_sdk_version":"0.0.1","device_low_power_mode":false,"app_unique_id":"org.wikimedia.wikipedia"},"user_triggered":false},{"id":"7d58109e-e156-42c2-aa27-ded0eba22593","session_id":"84d0b81b-beb4-4eeb-b1ab-3bf2575edd26","timestamp":"2025-01-20T13:59:04.847Z","type":"lifecycle_view_controller","lifecycle_view_controller":{"type":"viewWillAppear","class_name":"ExploreCardViewController"},"attribute":{"thread_name":"com.apple.main-thread","device_name":"iPhone 15 Pro","device_model":"Simulator iPhone 15 Pro","device_manufacturer":"Apple","device_type":"phone","device_is_foldable":false,"device_is_physical":false,"device_density_dpi":480,"device_width_px":1179,"device_height_px":2556,"device_density":3,"device_locale":"en_IN","os_name":"iOS","os_version":"17.4","platform":"ios","network_type":"wifi","network_generation":"unknown","network_provider":"unknown","installation_id":"6e59eb43-73d3-4829-87d1-d4f1a184725b","user_id":"test_user_id","device_cpu_arch":"x86_64","app_version":"7.5.6","app_build":"0","measure_sdk_version":"0.0.1","device_low_power_mode":false,"app_unique_id":"org.wikimedia.wikipedia"},"user_triggered":false},{"id":"ff19907d-1692-459c-8fc2-90885d7acf0e","session_id":"84d0b81b-beb4-4eeb-b1ab-3bf2575edd26","timestamp":"2025-01-20T13:59:04.858Z","type":"lifecycle_view_controller","lifecycle_view_controller":{"type":"viewWillAppear","class_name":"ExploreCardViewController"},"attribute":{"thread_name":"com.apple.main-thread","device_name":"iPhone 15 Pro","device_model":"Simulator iPhone 15 Pro","device_manufacturer":"Apple","device_type":"phone","device_is_foldable":false,"device_is_physical":false,"device_density_dpi":480,"device_width_px":1179,"device_height_px":2556,"device_density":3,"device_locale":"en_IN","os_name":"iOS","os_version":"17.4","platform":"ios","network_type":"wifi","network_generation":"unknown","network_provider":"unknown","installation_id":"6e59eb43-73d3-4829-87d1-d4f1a184725b","user_id":"test_user_id","device_cpu_arch":"x86_64","app_version":"7.5.6","app_build":"0","measure_sdk_version":"0.0.1","device_low_power_mode":false,"app_unique_id":"org.wikimedia.wikipedia"},"user_triggered":false},{"id":"c71da256-cddd-422c-85ac-f4cf8f36a116","session_id":"84d0b81b-beb4-4eeb-b1ab-3bf2575edd26","timestamp":"2025-01-20T13:59:04.867Z","type":"lifecycle_view_controller","lifecycle_view_controller":{"type":"viewWillAppear","class_name":"ExploreCardViewController"},"attribute":{"thread_name":"com.apple.main-thread","device_name":"iPhone 15 Pro","device_model":"Simulator iPhone 15 Pro","device_manufacturer":"Apple","device_type":"phone","device_is_foldable":false,"device_is_physical":false,"device_density_dpi":480,"device_width_px":1179,"device_height_px":2556,"device_density":3,"device_locale":"en_IN","os_name":"iOS","os_version":"17.4","platform":"ios","network_type":"wifi","network_generation":"unknown","network_provider":"unknown","installation_id":"6e59eb43-73d3-4829-87d1-d4f1a184725b","user_id":"test_user_id","device_cpu_arch":"x86_64","app_version":"7.5.6","app_build":"0","measure_sdk_version":"0.0.1","device_low_power_mode":false,"app_unique_id":"org.wikimedia.wikipedia"},"user_triggered":false},{"id":"6d5f8609-b933-422c-b36f-ca8054e20e73","session_id":"84d0b81b-beb4-4eeb-b1ab-3bf2575edd26","timestamp":"2025-01-20T13:59:04.877Z","type":"lifecycle_view_controller","lifecycle_view_controller":{"type":"viewWillAppear","class_name":"ExploreCardViewController"},"attribute":{"thread_name":"com.apple.main-thread","device_name":"iPhone 15 Pro","device_model":"Simulator iPhone 15 Pro","device_manufacturer":"Apple","device_type":"phone","device_is_foldable":false,"device_is_physical":false,"device_density_dpi":480,"device_width_px":1179,"device_height_px":2556,"device_density":3,"device_locale":"en_IN","os_name":"iOS","os_version":"17.4","platform":"ios","network_type":"wifi","network_generation":"unknown","network_provider":"unknown","installation_id":"6e59eb43-73d3-4829-87d1-d4f1a184725b","user_id":"test_user_id","device_cpu_arch":"x86_64","app_version":"7.5.6","app_build":"0","measure_sdk_version":"0.0.1","device_low_power_mode":false,"app_unique_id":"org.wikimedia.wikipedia"},"user_triggered":false},{"id":"e5feb1d2-a941-4745-bc7f-e27001665ef5","session_id":"84d0b81b-beb4-4eeb-b1ab-3bf2575edd26","timestamp":"2025-01-20T13:59:04.887Z","type":"lifecycle_view_controller","lifecycle_view_controller":{"type":"viewWillAppear","class_name":"ExploreCardViewController"},"attribute":{"thread_name":"com.apple.main-thread","device_name":"iPhone 15 Pro","device_model":"Simulator iPhone 15 Pro","device_manufacturer":"Apple","device_type":"phone","device_is_foldable":false,"device_is_physical":false,"device_density_dpi":480,"device_width_px":1179,"device_height_px":2556,"device_density":3,"device_locale":"en_IN","os_name":"iOS","os_version":"17.4","platform":"ios","network_type":"wifi","network_generation":"unknown","network_provider":"unknown","installation_id":"6e59eb43-73d3-4829-87d1-d4f1a184725b","user_id":"test_user_id","device_cpu_arch":"x86_64","app_version":"7.5.6","app_build":"0","measure_sdk_version":"0.0.1","device_low_power_mode":false,"app_unique_id":"org.wikimedia.wikipedia"},"user_triggered":false},{"id":"2304b766-63d2-4998-8c42-dbdf562706cb","session_id":"84d0b81b-beb4-4eeb-b1ab-3bf2575edd26","timestamp":"2025-01-20T13:59:05.060Z","type":"cpu_usage","cpu_usage":{"num_cores":12,"clock_speed":2600000000,"start_time":0,"uptime":0,"utime":0,"cutime":0,"cstime":0,"stime":0,"interval":3000,"percentage_usage":43.1},"attribute":{"thread_name":"com.apple.main-thread","device_name":"iPhone 15 Pro","device_model":"Simulator iPhone 15 Pro","device_manufacturer":"Apple","device_type":"phone","device_is_foldable":false,"device_is_physical":false,"device_density_dpi":480,"device_width_px":1179,"device_height_px":2556,"device_density":3,"device_locale":"en_IN","os_name":"iOS","os_version":"17.4","platform":"ios","network_type":"wifi","network_generation":"unknown","network_provider":"unknown","installation_id":"6e59eb43-73d3-4829-87d1-d4f1a184725b","user_id":"test_user_id","device_cpu_arch":"x86_64","app_version":"7.5.6","app_build":"0","measure_sdk_version":"0.0.1","device_low_power_mode":false,"app_unique_id":"org.wikimedia.wikipedia"},"user_triggered":false},{"id":"798bfdae-32e8-4d96-ad43-0a0649671fd4","session_id":"84d0b81b-beb4-4eeb-b1ab-3bf2575edd26","timestamp":"2025-01-20T13:59:05.076Z","type":"memory_usage_absolute","memory_usage_absolute":{"interval":2000,"used_memory":132624,"max_memory":16777216},"attribute":{"thread_name":"com.apple.main-thread","device_name":"iPhone 15 Pro","device_model":"Simulator iPhone 15 Pro","device_manufacturer":"Apple","device_type":"phone","device_is_foldable":false,"device_is_physical":false,"device_density_dpi":480,"device_width_px":1179,"device_height_px":2556,"device_density":3,"device_locale":"en_IN","os_name":"iOS","os_version":"17.4","platform":"ios","network_type":"wifi","network_generation":"unknown","network_provider":"unknown","installation_id":"6e59eb43-73d3-4829-87d1-d4f1a184725b","user_id":"test_user_id","device_cpu_arch":"x86_64","app_version":"7.5.6","app_build":"0","measure_sdk_version":"0.0.1","device_low_power_mode":false,"app_unique_id":"org.wikimedia.wikipedia"},"user_triggered":false}]}